Workbook

Sheet Lists
A1: Category
A2: Housing - Rent
A3: Groceries
A4: Dining & Coffee
A5: Utilities & Phone
A6: Transport
A7: Fitness & Memberships
A8: Health & Pharmacy
A9: Shopping
A10: Beauty & Personal Care
A11: Home & Household
A12: Entertainment & Experiences
... A23: Income - Other Credit

Sheet Transactions
A1: Date | B1: Description | C1: Details | D1: Category | E1: Amount (AUD) | F1: Debit (AUD) | G1: Credit (AUD) | H1: Statement Balance (AUD) | I1: Month | J1: Parse Status | K1: Source Page | L1: Raw PDF text
A2: 45962 | B2: HAWAIIAN1734212522763 PARIS FR | C2: Card xx6220 USD 23.00 | Value Date 29/10/2025 | D2: Other | E2: -35.16 | F2: 35.16 | G2: 0 | H2: 7624.16 | I2: 2025-11 | J2: High confidence | K2: 1 | L2: 01 Nov HAWAIIAN1734212522763 PARIS FR FRA | Card xx6220 USD 23.00 | Value Date 29/10/2025 35.16 7,624.16 CR | 0303
A3: 45962 | B3: International Transaction Fee | C3: Value Date 29/10/2025 | D3: Bank Fees | E3: -1.23 | F3: 1.23 | G3: 0 | H3: 7622.93 | I3: 2025-11 | J3: High confidence | K3: 1 | L3: 01 Nov International Transaction Fee | Value Date 29/10/2025 1.23 7,622.93 CR | ZZ258R3
A4: 45962 | B4: THE TASTE OF ASIAN PTY MASCOT AUS | C4: Card xx0018 | Value Date 30/10/2025 | D4: Other | E4: -20 | F4: 20 | G4: 0 | H4: 7602.93 | I4: 2025-11 | J4: High confidence | K4: 1 | L4: 01 Nov THE TASTE OF ASIAN PTY MASCOT AUS | Card xx0018 | Value Date 30/10/2025 20.00 7,602.93 CR | 3162.10484.1.6
A5: 45962 | B5: UBER *TRIP HELP.UBER.C 14518236738 | C5: Card xx0018 | Value Date 31/10/2025 | TELLO MOBILE ATLANTA GA USA | Card xx0018 USD 11.78 | Value Date 30/10/2025 | D5: Transport | E5: -5 | F5: 5 | G5: 0 | H5: 7597.93 | I5: 2025-11 | J5: High confidence | K5: 1 | L5: 01 Nov UBER *TRIP HELP.UBER.C 14518236738 AU AU | Card xx0018 | Value Date 31/10/2025 5.00 7,597.93 CR | * | * 01 Nov TELLO MOBILE ATLANTA GA USA | Card xx0018 USD 11.78 | Value Date 30/10/2025 18.01 7,579.92 CR
A6: 45962 | B6: International Transaction Fee | C6: Value Date 29/10/2025 | D6: Bank Fees | E6: -18.64 | F6: 18.64 | G6: 0 | H6: 7579.29 | I6: 2025-11 | J6: Amount mismatch: columns -0.63, balance delta -18.64; used balance | K6: 1 | L6: 01 Nov International Transaction Fee | Value Date 29/10/2025 0.63 7,579.29 CR
A7: 45962 | B7: Liv Eat Mascot NS AUS | C7: Card xx0018 | Value Date 29/10/2025 | D7: Other | E7: -6.09 | F7: 6.09 | G7: 0 | H7: 7573.2 | I7: 2025-11 | J7: High confidence | K7: 1 | L7: 01 Nov Liv Eat Mascot NS AUS | Card xx0018 | Value Date 29/10/2025 6.09 7,573.20 CR
A8: 45962 | B8: UBER *TRIP HELP.UBER.C 14518236738 | C8: Card xx0018 | Value Date 30/10/2025 | D8: Transport | E8: -5 | F8: 5 | G8: 0 | H8: 7568.2 | I8: 2025-11 | J8: High confidence | K8: 1 | L8: 01 Nov UBER *TRIP HELP.UBER.C 14518236738 AU AU | Card xx0018 | Value Date 30/10/2025 5.00 7,568.20 CR
A9: 45962 | B9: UBER *TRIP HELP.UBER.C 14518236738 | C9: Card xx0018 | Value Date 30/10/2025 | D9: Transport | E9: -67.79 | F9: 67.79 | G9: 0 | H9: 7500.41 | I9: 2025-11 | J9: High confidence | K9: 1 | L9: 01 Nov UBER *TRIP HELP.UBER.C 14518236738 AU AU | Card xx0018 | Value Date 30/10/2025 67.79 7,500.41 CR
A10: 45962 | B10: UBER *TRIP HELP.UBER.C 14518236738 | C10: Card xx0018 | Value Date 30/10/2025 | D10: Transport | E10: -5 | F10: 5 | G10: 0 | H10: 7495.41 | I10: 2025-11 | J10: High confidence | K10: 2 | L10: 01 Nov UBER *TRIP HELP.UBER.C 14518236738 AU AU | Card xx0018 | Value Date 30/10/2025 5.00 7,495.41 CR
A11: 45964 | B11: Direct Debit 545383 Telstra Services | C11: hn4vs2tp | D11: Utilities & Phone | E11: -10 | F11: 10 | G11: 0 | H11: 7485.41 | I11: 2025-11 | J11: High confidence | K11: 2 | L11: 03 Nov Direct Debit 545383 Telstra Services | hn4vs2tp 10.00 7,485.41 CR
A12: 45964 | B12: Direct Debit 012495 GU HEALTH D/DBT | C12: 29497443 | D12: Health & Pharmacy | E12: -65.76 | F12: 65.76 | G12: 0 | H12: 7419.65 | I12: 2025-11 | J12: High confidence | K12: 2 | L12: 03 Nov Direct Debit 012495 GU HEALTH D/DBT | 29497443 65.76 7,419.65 CR
A13: 45965 | B13: KEN'S MARKET 75-116 SEATTLE WA | C13: Card xx0018 USD 2.75 | Value Date 01/11/2025 | D13: Other | E13: -4.21 | F13: 4.21 | G13: 0 | H13: 7415.44 | I13: 2025-11 | J13: High confidence | K13: 2 | L13: 04 Nov KEN'S MARKET 75-116 SEATTLE WA USA | Card xx0018 USD 2.75 | Value Date 01/11/2025 4.21 7,415.44 CR
... A37: 45968 | B37: TH*Greencare Clinics Sydney NS AUS | C37: Card xx0018 | Value Date 06/11/2025 | SQ *Y'NO DY Dee Why AU | D37: Health & Pharmacy | E37: -99 | F37: 99 | G37: 0 | H37: 5030.95 | I37: 2025-11 | J37: High confidence | K37: 3 | L37: 07 Nov TH*Greencare Clinics Sydney NS AUS | 0303 Card xx0018 | Value Date 06/11/2025 99.00 5,030.95 CR | ZZ258R3 07 Nov SQ *Y'NO DY Dee Why AU 4.50 5,026.45 CR
A38: 45968 | B38: SQ *TOASTIESMITH TGV Sydney AU | D38: Other | E38: -13.13 | F38: 13.13 | G38: 0 | H38: 5017.82 | I38: 2025-11 | J38: Amount mismatch: columns -8.63, balance delta -13.13; used balance | K38: 3 | L38: 07 Nov SQ *TOASTIESMITH TGV Sydney AU 8.63 5,017.82 CR
A39: 45969 | B39: TRANSPORTFORNSW OPAL CHIPPENDALE | C39: Card xx6220 | Value Date 07/11/2025 | D39: Transport | E39: -60 | F39: 60 | G39: 0 | H39: 4957.82 | I39: 2025-11 | J39: High confidence | K39: 3 | L39: 08 Nov TRANSPORTFORNSW OPAL CHIPPENDALE AUS | 3162.10485.2.6 Card xx6220 | Value Date 07/11/2025 60.00 4,957.82 CR
A40: 45969 | B40: UBER *TRIP HELP.UBER.C 14518236738 | C40: Card xx0018 | Value Date 06/11/2025 | D40: Transport | E40: -103.02 | F40: 103.02 | G40: 0 | H40: 4854.8 | I40: 2025-11 | J40: High confidence | K40: 3 | L40: 08 Nov UBER *TRIP HELP.UBER.C 14518236738 AU AU | Card xx0018 | Value Date 06/11/2025 103.02 4,854.80 CR
A41: 45969 | B41: SQ *PAGES & PAGES HONO Honolulu | C41: Card xx0018 USD 3.99 | Value Date 06/11/2025 | D41: Other | E41: -6.18 | F41: 6.18 | G41: 0 | H41: 4848.62 | I41: 2025-11 | J41: High confidence | K41: 3 | L41: 08 Nov SQ *PAGES & PAGES HONO Honolulu HI USA | Card xx0018 USD 3.99 | Value Date 06/11/2025 6.18 4,848.62 CR
A42: 45969 | B42: International Transaction Fee | C42: Value Date 05/11/2025 | D42: Bank Fees | E42: -0.22 | F42: 0.22 | G42: 0 | H42: 4848.4 | I42: 2025-11 | J42: High confidence | K42: 3 | L42: 08 Nov International Transaction Fee | Value Date 05/11/2025 0.22 4,848.40 CR
A43: 45969 | B43: WENDY'S 13238-615 SEATTLE WA | C43: Card xx0018 USD 5.81 | Value Date 06/11/2025 | D43: Other | E43: -8.97 | F43: 8.97 | G43: 0 | H43: 4839.43 | I43: 2025-11 | J43: High confidence | K43: 3 | L43: 08 Nov WENDY'S 13238-615 SEATTLE WA USA | Card xx0018 USD 5.81 | Value Date 06/11/2025 8.97 4,839.43 CR
A44: 45969 | B44: International Transaction Fee | C44: Value Date 05/11/2025 | D44: Bank Fees | E44: -0.31 | F44: 0.31 | G44: 0 | H44: 4839.12 | I44: 2025-11 | J44: High confidence | K44: 3 | L44: 08 Nov International Transaction Fee | Value Date 05/11/2025 0.31 4,839.12 CR
A45: 45969 | B45: PIKE&PINE ST2275 SEATTLE WA USA | C45: Card xx0018 USD 5.82 | Value Date 06/11/2025 | D45: Other | E45: -8.98 | F45: 8.98 | G45: 0 | H45: 4830.14 | I45: 2025-11 | J45: High confidence | K45: 4 | L45: 08 Nov PIKE&PINE ST2275 SEATTLE WA USA | Card xx0018 USD 5.82 | Value Date 06/11/2025 8.98 4,830.14 CR
A46: 45969 | B46: International Transaction Fee | C46: Value Date 05/11/2025 | D46: Bank Fees | E46: -0.31 | F46: 0.31 | G46: 0 | H46: 4829.83 | I46: 2025-11 | J46: High confidence | K46: 4 | L46: 08 Nov International Transaction Fee | Value Date 05/11/2025 0.31 4,829.83 CR
A47: 45969 | B47: SQ *SACREBLEU | CANELE dee why AU | D47: Dining & Coffee | E47: -8.12 | F47: 8.12 | G47: 0 | H47: 4821.71 | I47: 2025-11 | J47: High confidence | K47: 4 | L47: 08 Nov SQ *SACREBLEU | CANELE dee why AU 8.12 4,821.71 CR
A48: 45969 | B48: COLES 0784 DEE WHY AU | D48: Groceries | E48: -24.89 | F48: 24.89 | G48: 0 | H48: 4796.82 | I48: 2025-11 | J48: High confidence | K48: 4 | L48: 08 Nov COLES 0784 DEE WHY AU 24.89 4,796.82 CR
A49: 45970 | B49: SQ *Y'NO DY Dee Why AU | D49: Other | E49: -4.5 | F49: 4.5 | G49: 0 | H49: 4792.32 | I49: 2025-11 | J49: High confidence | K49: 4 | L49: 09 Nov SQ *Y'NO DY Dee Why AU 4.50 4,792.32 CR
A50: 45970 | B50: SQ *SACREBLEU | CANELE dee why AU | D50: Dining & Coffee | E50: -14.2 | F50: 14.2 | G50: 0 | H50: 4778.12 | I50: 2025-11 | J50: High confidence | K50: 4 | L50: 09 Nov SQ *SACREBLEU | CANELE dee why AU 14.20 4,778.12 CR
A51: 45971 | B51: Subway Kent 24 Market StrAU | D51: Dining & Coffee | E51: -4.5 | F51: 4.5 | G51: 0 | H51: 4773.62 | I51: 2025-11 | J51: High confidence | K51: 4 | L51: 10 Nov Subway Kent 24 Market StrAU 4.50 4,773.62 CR
A52: 45971 | B52: Subway Dee Why 7 Oaks AvenueAU | D52: Dining & Coffee | E52: -2.95 | F52: 2.95 | G52: 0 | H52: 4770.67 | I52: 2025-11 | J52: High confidence | K52: 4 | L52: 10 Nov Subway Dee Why 7 Oaks AvenueAU 2.95 4,770.67 CR
A53: 45972 | B53: SP TEA LIFE NORTH SAINT M NS AUS | C53: Card xx6220 | Value Date 09/11/2025 | D53: Dining & Coffee | E53: -64.7 | F53: 64.7 | G53: 0 | H53: 4705.97 | I53: 2025-11 | J53: High confidence | K53: 4 | L53: 11 Nov SP TEA LIFE NORTH SAINT M NS AUS | Card xx6220 | Value Date 09/11/2025 64.70 4,705.97 CR
A54: 45972 | B54: Return UBER *TRIP HELP.UBER.C | C54: Card xx0018 | Value Date 09/11/2025 | D54: Income - Refund/Reimbursement | E54: 0.02 | F54: 0 | G54: 0.02 | H54: 4705.99 | I54: 2025-11 | J54: High confidence | K54: 4 | L54: 11 Nov Return UBER *TRIP HELP.UBER.C 1451823673 | Card xx0018 | Value Date 09/11/2025 0.02 4,705.99 CR
A55: 45972 | B55: UBER *TRIP HELP.UBER.C 14518236738 | C55: Card xx0018 | Value Date 09/11/2025 | D55: Transport | E55: -3 | F55: 3 | G55: 0 | H55: 4702.99 | I55: 2025-11 | J55: High confidence | K55: 4 | L55: 11 Nov UBER *TRIP HELP.UBER.C 14518236738 AU AU | Card xx0018 | Value Date 09/11/2025 3.00 4,702.99 CR
A56: 45972 | B56: GREENHOUSE KIRRIBILLI Kirribilli NS | C56: Card xx0018 | Value Date 09/11/2025 | D56: Other | E56: -43.2 | F56: 43.2 | G56: 0 | H56: 4659.79 | I56: 2025-11 | J56: High confidence | K56: 4 | L56: 11 Nov GREENHOUSE KIRRIBILLI Kirribilli NS AUS | Card xx0018 | Value Date 09/11/2025 43.20 4,659.79 CR
A57: 45972 | B57: UBER *TRIP HELP.UBER.C 14518236738 | C57: Card xx0018 | Value Date 09/11/2025 | D57: Transport | E57: -12.75 | F57: 12.75 | G57: 0 | H57: 4647.04 | I57: 2025-11 | J57: High confidence | K57: 4 | L57: 11 Nov UBER *TRIP HELP.UBER.C 14518236738 AU AU | V06.00.37 | Card xx0018 | Value Date 09/11/2025 12.75 4,647.04 CR
A58: 45972 | B58: BWS LIQUOR 1653 KIRRIBILLI NS AUS | C58: Card xx0018 | Value Date 09/11/2025 | D58: Dining & Coffee | E58: -6.5 | F58: 6.5 | G58: 0 | H58: 4640.54 | I58: 2025-11 | J58: High confidence | K58: 4 | L58: 11 Nov BWS LIQUOR 1653 KIRRIBILLI NS AUS | Card xx0018 | SL.R3.S141.D338.O Value Date 09/11/2025 6.50 4,640.54 CR
A59: 45972 | B59: UBER *TRIP HELP.UBER.C 14518236738 | C59: Card xx0018 | Value Date 09/11/2025 | D59: Transport | E59: -16.03 | F59: 16.03 | G59: 0 | H59: 4624.51 | I59: 2025-11 | J59: High confidence | K59: 4 | L59: 11 Nov UBER *TRIP HELP.UBER.C 14518236738 AU AU | Card xx0018 | Value Date 09/11/2025 16.03 4,624.51 CR | 0303
A60: 45972 | B60: COLES 0784 DEE WHY 02 AUS | C60: Card xx0018 | Value Date 07/11/2025 | D60: Groceries | E60: -64.39 | F60: 64.39 | G60: 0 | H60: 4560.12 | I60: 2025-11 | J60: High confidence | K60: 4 | L60: 11 Nov COLES 0784 DEE WHY 02 AUS | Card xx0018 | ZZ258R3 | Value Date 07/11/2025 64.39 4,560.12 CR
A61: 45972 | B61: GARDENIA ESPRESSO SYDNEY NS AUS | C61: Card xx0018 | Value Date 07/11/2025 | D61: Dining & Coffee | E61: -11.5 | F61: 11.5 | G61: 0 | H61: 4548.62 | I61: 2025-11 | J61: High confidence | K61: 4 | L61: 11 Nov GARDENIA ESPRESSO SYDNEY NS AUS | Card xx0018 | 3162.10485.2.6 Value Date 07/11/2025 11.50 4,548.62 CR
A62: 45972 | B62: B5 Cafe Narraweena NS AUS | C62: Card xx0018 | Value Date 08/11/2025 | D62: Dining & Coffee | E62: -22.73 | F62: 22.73 | G62: 0 | H62: 4525.89 | I62: 2025-11 | J62: High confidence | K62: 4 | L62: 11 Nov B5 Cafe Narraweena NS AUS | Card xx0018 | Value Date 08/11/2025 22.73 4,525.89 CR
A63: 45972 | B63: UBER *EATS HELP.UBER.C Sydney AU | C63: Card xx0018 | Value Date 07/11/2025 | D63: Other | E63: -258.58 | F63: 258.58 | G63: 0 | H63: 4267.31 | I63: 2025-11 | J63: High confidence | K63: 4 | L63: 11 Nov UBER *EATS HELP.UBER.C Sydney AU AUS | Card xx0018 | Value Date 07/11/2025 258.58 4,267.31 CR
A64: 45972 | B64: LOCALI BY ROMEOS SYDNEY NS AUS | C64: Card xx0018 | Value Date 07/11/2025 | D64: Other | E64: -17.88 | F64: 17.88 | G64: 0 | H64: 4249.43 | I64: 2025-11 | J64: High confidence | K64: 4 | L64: 11 Nov LOCALI BY ROMEOS SYDNEY NS AUS | Card xx0018 | Value Date 07/11/2025 17.88 4,249.43 CR
A65: 45972 | B65: SMP*Hero Sushi Dee Why Dee Why02 | D65: Dining & Coffee | E65: -4.55 | F65: 4.55 | G65: 0 | H65: 4244.88 | I65: 2025-11 | J65: High confidence | K65: 4 | L65: 11 Nov SMP*Hero Sushi Dee Why Dee Why02 AU 4.55 4,244.88 CR
A66: 45972 | B66: COLES 0784 DEE WHY AU | D66: Groceries | E66: -6.3 | F66: 6.3 | G66: 0 | H66: 4238.58 | I66: 2025-11 | J66: High confidence | K66: 4 | L66: 11 Nov COLES 0784 DEE WHY AU 6.30 4,238.58 CR
A67: 45973 | B67: DD *DOORDASH OPORTO MELBOURNE | C67: Card xx6220 | Value Date 10/11/2025 | D67: Other | E67: -7 | F67: 7 | G67: 0 | H67: 4231.58 | I67: 2025-11 | J67: High confidence | K67: 4 | L67: 12 Nov DD *DOORDASH OPORTO MELBOURNE VI AUS | Card xx6220 | Value Date 10/11/2025 7.00 4,231.58 CR
A68: 45973 | B68: NEXGEN PHARMA CASTLE HILL NS AUS | C68: Card xx6220 | Value Date 10/11/2025 | D68: Health & Pharmacy | E68: -305 | F68: 305 | G68: 0 | H68: 3926.58 | I68: 2025-11 | J68: High confidence | K68: 5 | L68: 12 Nov NEXGEN PHARMA CASTLE HILL NS AUS | Card xx6220 | Value Date 10/11/2025 305.00 3,926.58 CR
A69: 45973 | B69: TRANSPORTFORNSW TAP SYDNEY AUS | C69: Card xx0018 | Value Date 10/11/2025 | D69: Transport | E69: -4.03 | F69: 4.03 | G69: 0 | H69: 3922.55 | I69: 2025-11 | J69: High confidence | K69: 5 | L69: 12 Nov TRANSPORTFORNSW TAP SYDNEY AUS | Card xx0018 | Value Date 10/11/2025 4.03 3,922.55 CR
A70: 45973 | B70: OH MATCHA SYDNEY AUS | C70: Card xx0018 | Value Date 10/11/2025 | D70: Other | E70: -7.31 | F70: 7.31 | G70: 0 | H70: 3915.24 | I70: 2025-11 | J70: High confidence | K70: 5 | L70: 12 Nov OH MATCHA SYDNEY AUS | Card xx0018 | Value Date 10/11/2025 7.31 3,915.24 CR
A71: 45973 | B71: MARGOT ESPRESSO SYDNEY NS AUS | C71: Card xx0018 | Value Date 10/11/2025 | MARKET ST CAFE SYDNEY NS AUS | Card xx0018 | Value Date 10/11/2025 | D71: Dining & Coffee | E71: -4.08 | F71: 4.08 | G71: 0 | H71: 3911.16 | I71: 2025-11 | J71: High confidence | K71: 5 | L71: 12 Nov MARGOT ESPRESSO SYDNEY NS AUS | Card xx0018 | Value Date 10/11/2025 4.08 3,911.16 CR | =àXOÌ3) 12 Nov 2 MARKET ST CAFE SYDNEY NS AUS | Card xx0018 | Value Date 10/11/2025 4.50 3,906.66 CR
A72: 45973 | B72: SQ *Y'NO DY Dee Why AU | D72: Other | E72: -9 | F72: 9 | G72: 0 | H72: 3902.16 | I72: 2025-11 | J72: Amount mismatch: columns -4.50, balance delta -9.00; used balance | K72: 5 | L72: 12 Nov SQ *Y'NO DY Dee Why AU 4.50 3,902.16 CR
A73: 45973 | B73: SUPERB SUNNY PTY LTD Sydney AU | D73: Other | E73: -7.4 | F73: 7.4 | G73: 0 | H73: 3894.76 | I73: 2025-11 | J73: High confidence | K73: 5 | L73: 12 Nov SUPERB SUNNY PTY LTD Sydney AU 7.40 3,894.76 CR
A74: 45973 | B74: SMP*Hero Sushi Dee Why Dee Why02 | D74: Dining & Coffee | E74: -4.55 | F74: 4.55 | G74: 0 | H74: 3890.21 | I74: 2025-11 | J74: High confidence | K74: 5 | L74: 12 Nov SMP*Hero Sushi Dee Why Dee Why02 AU 4.55 3,890.21 CR
A75: 45973 | B75: Direct Debit 507156 MBAUDPayments | C75: AMBITIONS_TP9cGCtc | D75: Fitness & Memberships | E75: -68 | F75: 68 | G75: 0 | H75: 3822.21 | I75: 2025-11 | J75: High confidence | K75: 5 | L75: 12 Nov Direct Debit 507156 MBAUDPayments | AMBITIONS_TP9cGCtc 68.00 3,822.21 CR
A76: 45974 | B76: FLYING HAT SYDNEY AUS | C76: Card xx0018 | Value Date 11/11/2025 | D76: Other | E76: -12.13 | F76: 12.13 | G76: 0 | H76: 3810.08 | I76: 2025-11 | J76: High confidence | K76: 5 | L76: 13 Nov FLYING HAT SYDNEY AUS | Card xx0018 | Value Date 11/11/2025 12.13 3,810.08 CR
A77: 45974 | B77: MARGOT ESPRESSO SYDNEY NS AUS | C77: Card xx0018 | Value Date 11/11/2025 | D77: Dining & Coffee | E77: -4.08 | F77: 4.08 | G77: 0 | H77: 3806 | I77: 2025-11 | J77: High confidence | K77: 5 | L77: 13 Nov MARGOT ESPRESSO SYDNEY NS AUS | Card xx0018 | V06.00.37 | Value Date 11/11/2025 4.08 3,806.00 CR
A78: 45974 | B78: IGA DEE WHY L0347 DEE WHY NS AUS | C78: Card xx0018 | Value Date 11/11/2025 | D78: Groceries | E78: -3.09 | F78: 3.09 | G78: 0 | H78: 3802.91 | I78: 2025-11 | J78: High confidence | K78: 5 | L78: 13 Nov IGA DEE WHY L0347 DEE WHY NS AUS | Card xx0018 | Value Date 11/11/2025 3.09 3,802.91 CR | SL.R3.S141.D338.O
A79: 45974 | B79: WOOLWORTHS 1472 DEE WHY NS AUS | C79: Card xx0018 | Value Date 11/11/2025 | SQ *THE SNEAKER LAUNDR Sydney AU | D79: Groceries | E79: -2.2 | F79: 2.2 | G79: 0 | H79: 3800.71 | I79: 2025-11 | J79: High confidence | K79: 5 | L79: 13 Nov WOOLWORTHS 1472 DEE WHY NS AUS | Card xx0018 | Value Date 11/11/2025 2.20 3,800.71 CR | 0303 13 Nov SQ *THE SNEAKER LAUNDR Sydney AU 14.18 3,786.53 CR
A80: 45974 | B80: Direct Debit 518073 Crunch Fitness - | C80: EZYPAYID_81315353 | D80: Fitness & Memberships | E80: -55.08 | F80: 55.08 | G80: 0 | H80: 3745.63 | I80: 2025-11 | J80: Amount mismatch: columns -40.90, balance delta -55.08; used balance | K80: 5 | L80: 13 Nov Direct Debit 518073 Crunch Fitness - | ZZ258R3 EZYPAYID_81315353 40.90 3,745.63 CR
A81: 45975 | B81: ALLIANCE PEST SOLUTION NARWEE | C81: Card xx0018 | Value Date 12/11/2025 | D81: Home & Household | E81: -198 | F81: 198 | G81: 0 | H81: 3547.63 | I81: 2025-11 | J81: High confidence | K81: 5 | L81: 14 Nov ALLIANCE PEST SOLUTION NARWEE AUS | Card xx0018 | Value Date 12/11/2025 198.00 3,547.63 CR | 3162.10486.3.6
A82: 45975 | B82: HOLEY MOLEY AUSTRALIA ABBOTSFORD | C82: Card xx0018 | Value Date 13/11/2025 | D82: Other | E82: -80.58 | F82: 80.58 | G82: 0 | H82: 3467.05 | I82: 2025-11 | J82: High confidence | K82: 5 | L82: 14 Nov HOLEY MOLEY AUSTRALIA ABBOTSFORD VI AUS | Card xx0018 | Value Date 13/11/2025 80.58 3,467.05 CR
A83: 45975 | B83: KFC Sydney Central Sydney Centra AU | C83: Card xx0018 | Value Date 12/11/2025 | D83: Dining & Coffee | E83: -8.95 | F83: 8.95 | G83: 0 | H83: 3458.1 | I83: 2025-11 | J83: High confidence | K83: 5 | L83: 14 Nov KFC Sydney Central Sydney Centra AU AUS | Card xx0018 | Value Date 12/11/2025 8.95 3,458.10 CR
A84: 45975 | B84: SQ *SACREBLEU | CANELE dee why AU | D84: Dining & Coffee | E84: -8.62 | F84: 8.62 | G84: 0 | H84: 3449.48 | I84: 2025-11 | J84: High confidence | K84: 5 | L84: 14 Nov SQ *SACREBLEU | CANELE dee why AU 8.62 3,449.48 CR
A85: 45975 | B85: LS Supa Fresh Pty Ltd Sydney AU | D85: Other | E85: -6.62 | F85: 6.62 | G85: 0 | H85: 3442.86 | I85: 2025-11 | J85: High confidence | K85: 5 | L85: 14 Nov LS Supa Fresh Pty Ltd Sydney AU 6.62 3,442.86 CR
A86: 45975 | B86: SQ *SKITTLE LANE Sydney AU | D86: Dining & Coffee | E86: -17.74 | F86: 17.74 | G86: 0 | H86: 3425.12 | I86: 2025-11 | J86: High confidence | K86: 5 | L86: 14 Nov SQ *SKITTLE LANE Sydney AU 17.74 3,425.12 CR
A87: 45975 | B87: Bar Lucia Potts Point AU | D87: Other | E87: -79.17 | F87: 79.17 | G87: 0 | H87: 3345.95 | I87: 2025-11 | J87: High confidence | K87: 5 | L87: 14 Nov Bar Lucia Potts Point AU 79.17 3,345.95 CR
A88: 45976 | B88: MARGOT ESPRESSO SYDNEY NS AUS | C88: Card xx0018 | Value Date 13/11/2025 | MARKET ST CAFE SYDNEY NS AUS | Card xx0018 | Value Date 13/11/2025 | D88: Dining & Coffee | E88: -4.08 | F88: 4.08 | G88: 0 | H88: 3341.87 | I88: 2025-11 | J88: High confidence | K88: 5 | L88: 15 Nov MARGOT ESPRESSO SYDNEY NS AUS | Card xx0018 | Value Date 13/11/2025 4.08 3,341.87 CR | 15 Nov 2 MARKET ST CAFE SYDNEY NS AUS | Card xx0018 | Value Date 13/11/2025 4.50 3,337.37 CR
A89: 45976 | B89: SQ *WILBUR'S DELI - BR Brookvale AU | D89: Dining & Coffee | E89: -18.5 | F89: 18.5 | G89: 0 | H89: 3323.37 | I89: 2025-11 | J89: Amount mismatch: columns -14.00, balance delta -18.50; used balance | K89: 6 | L89: 15 Nov SQ *WILBUR'S DELI - BR Brookvale AU 14.00 3,323.37 CR
A90: 45976 | B90: Lindt Australia Brookvale AU | D90: Other | E90: -4.8 | F90: 4.8 | G90: 0 | H90: 3318.57 | I90: 2025-11 | J90: High confidence | K90: 6 | L90: 15 Nov Lindt Australia Brookvale AU 4.80 3,318.57 CR
A91: 45976 | B91: CHA MS PTY LTD Brookvale AU | D91: Other | E91: -7.01 | F91: 7.01 | G91: 0 | H91: 3311.56 | I91: 2025-11 | J91: High confidence | K91: 6 | L91: 15 Nov CHA MS PTY LTD Brookvale AU 7.01 3,311.56 CR
A92: 45976 | B92: COLES 0784 DEE WHY AU | D92: Groceries | E92: -18.7 | F92: 18.7 | G92: 0 | H92: 3292.86 | I92: 2025-11 | J92: High confidence | K92: 6 | L92: 15 Nov COLES 0784 DEE WHY AU 18.70 3,292.86 CR
A93: 45977 | B93: SQ *FRENCH BASKET Dee Why AU | D93: Other | E93: -13.15 | F93: 13.15 | G93: 0 | H93: 3279.71 | I93: 2025-11 | J93: High confidence | K93: 6 | L93: 16 Nov SQ *FRENCH BASKET Dee Why AU 13.15 3,279.71 CR
A94: 45977 | B94: Subway Dee Why 7 Oaks AvenueAU | D94: Dining & Coffee | E94: -2.95 | F94: 2.95 | G94: 0 | H94: 3276.76 | I94: 2025-11 | J94: High confidence | K94: 6 | L94: 16 Nov Subway Dee Why 7 Oaks AvenueAU 2.95 3,276.76 CR
A95: 45978 | B95: Direct Debit 545383 Telstra Services | C95: eak10r10 | D95: Utilities & Phone | E95: -70 | F95: 70 | G95: 0 | H95: 3206.76 | I95: 2025-11 | J95: High confidence | K95: 6 | L95: 17 Nov Direct Debit 545383 Telstra Services | eak10r10 70.00 3,206.76 CR
A96: 45979 | B96: TRANSPORTFORNSW OPAL CHIPPENDALE | C96: Card xx6220 | Value Date 16/11/2025 | D96: Transport | E96: -60 | F96: 60 | G96: 0 | H96: 3146.76 | I96: 2025-11 | J96: High confidence | K96: 6 | L96: 18 Nov TRANSPORTFORNSW OPAL CHIPPENDALE AUS | Card xx6220 | Value Date 16/11/2025 60.00 3,146.76 CR
A97: 45979 | B97: DD *DOORDASH OPORTO MELBOURNE | C97: Card xx6220 | Value Date 13/11/2025 | D97: Other | E97: -5.5 | F97: 5.5 | G97: 0 | H97: 3141.26 | I97: 2025-11 | J97: High confidence | K97: 6 | L97: 18 Nov DD *DOORDASH OPORTO MELBOURNE VI AUS | Card xx6220 | Value Date 13/11/2025 5.50 3,141.26 CR
A98: 45979 | B98: SQ *SKITTLE LANE Sydney AU | D98: Dining & Coffee | E98: -17.74 | F98: 17.74 | G98: 0 | H98: 3123.52 | I98: 2025-11 | J98: High confidence | K98: 6 | L98: 18 Nov SQ *SKITTLE LANE Sydney AU 17.74 3,123.52 CR
A99: 45979 | B99: TRANSPORTFORNSW TAP SYDNEY AUS | C99: Card xx0018 | Value Date 16/11/2025 | D99: Transport | E99: -6.34 | F99: 6.34 | G99: 0 | H99: 3117.18 | I99: 2025-11 | J99: High confidence | K99: 6 | L99: 18 Nov TRANSPORTFORNSW TAP SYDNEY AUS | Card xx0018 | Value Date 16/11/2025 6.34 3,117.18 CR
A100: 45979 | B100: HFM MONA VALE QPS MONA VALE AUS | C100: Card xx0018 | Value Date 16/11/2025 | D100: Groceries | E100: -13.34 | F100: 13.34 | G100: 0 | H100: 3103.84 | I100: 2025-11 | J100: High confidence | K100: 6 | L100: 18 Nov HFM MONA VALE QPS MONA VALE AUS | Card xx0018 | Value Date 16/11/2025 13.34 3,103.84 CR
A101: 45979 | B101: COTTON ON 2110 WARRINGAH NS AUS | C101: Card xx0018 | Value Date 15/11/2025 | D101: Shopping | E101: -32 | F101: 32 | G101: 0 | H101: 3071.84 | I101: 2025-11 | J101: High confidence | K101: 6 | L101: 18 Nov COTTON ON 2110 WARRINGAH NS AUS | Card xx0018 | Value Date 15/11/2025 32.00 3,071.84 CR | V06.00.37
A102: 45979 | B102: The Vicars Daughters Collaroy AU AUS | C102: Card xx0018 | Value Date 16/11/2025 | D102: Other | E102: -7.62 | F102: 7.62 | G102: 0 | H102: 3064.22 | I102: 2025-11 | J102: High confidence | K102: 6 | L102: 18 Nov The Vicars Daughters Collaroy AU AUS | Card xx0018 | Value Date 16/11/2025 7.62 3,064.22 CR
A103: 45979 | B103: FLANNERYS MONA VALE Mona Vale AU | C103: Card xx0018 | Value Date 16/11/2025 | D103: Groceries | E103: -19.57 | F103: 19.57 | G103: 0 | H103: 3044.65 | I103: 2025-11 | J103: High confidence | K103: 6 | L103: 18 Nov FLANNERYS MONA VALE Mona Vale AU AUS | SL.R3.S141.D338.O | Card xx0018 | Value Date 16/11/2025 19.57 3,044.65 CR
A104: 45979 | B104: WOOLWORTHS 1472 DEE WHY NS AUS | C104: Card xx0018 | Value Date 16/11/2025 | TRANSPORTFORNSW TAP SYDNEY AUS | Card xx0018 | Value Date 15/11/2025 | D104: Groceries | E104: -15.5 | F104: 15.5 | G104: 0 | H104: 3029.15 | I104: 2025-11 | J104: High confidence | K104: 6 | L104: 18 Nov WOOLWORTHS 1472 DEE WHY NS AUS | 0303 Card xx0018 | Value Date 16/11/2025 15.50 3,029.15 CR | ZZ258R3 18 Nov TRANSPORTFORNSW TAP SYDNEY AUS | Card xx0018 | Value Date 15/11/2025 4.03 3,025.12 CR
A105: 45979 | B105: JOHNNYGIOSPIZ* DEE WHY MARSDEN | C105: Card xx0018 | Value Date 15/11/2025 | D105: Dining & Coffee | E105: -16.54 | F105: 16.54 | G105: 0 | H105: 3012.61 | I105: 2025-11 | J105: Amount mismatch: columns -12.51, balance delta -16.54; used balance | K105: 6 | L105: 18 Nov JOHNNYGIOSPIZ* DEE WHY MARSDEN PARK NS A | 3162.10486.3.6 | Card xx0018 | Value Date 15/11/2025 12.51 3,012.61 CR
A106: 45979 | B106: TIYEB STORE PTY LTD SYDNEY NS AUS | C106: Card xx0018 | Value Date 14/11/2025 | D106: Groceries | E106: -5.04 | F106: 5.04 | G106: 0 | H106: 3007.57 | I106: 2025-11 | J106: High confidence | K106: 6 | L106: 18 Nov TIYEB STORE PTY LTD SYDNEY NS AUS | Card xx0018 | Value Date 14/11/2025 5.04 3,007.57 CR
A107: 45979 | B107: SUSHI HUB QVB SYDNEY NS AUS | C107: Card xx0018 | Value Date 13/11/2025 | D107: Dining & Coffee | E107: -9 | F107: 9 | G107: 0 | H107: 2998.57 | I107: 2025-11 | J107: High confidence | K107: 6 | L107: 18 Nov SUSHI HUB QVB SYDNEY NS AUS | Card xx0018 | Value Date 13/11/2025 9.00 2,998.57 CR
A108: 45979 | B108: B5 Cafe Narraweena NS AUS | C108: Card xx0018 | Value Date 15/11/2025 | D108: Dining & Coffee | E108: -18.66 | F108: 18.66 | G108: 0 | H108: 2979.91 | I108: 2025-11 | J108: High confidence | K108: 6 | L108: 18 Nov B5 Cafe Narraweena NS AUS | Card xx0018 | Value Date 15/11/2025 18.66 2,979.91 CR
A109: 45979 | B109: Guzman Y Gomez Surry Hills AU AUS | C109: Card xx0018 | Value Date 14/11/2025 | D109: Dining & Coffee | E109: -11.8 | F109: 11.8 | G109: 0 | H109: 2968.11 | I109: 2025-11 | J109: High confidence | K109: 6 | L109: 18 Nov Guzman Y Gomez Surry Hills AU AUS | Card xx0018 | Value Date 14/11/2025 11.80 2,968.11 CR
A110: 45979 | B110: Northen Beaches Denta DEE WHY AUS | C110: Card xx0018 | Value Date 14/11/2025 | D110: Other | E110: -11.77 | F110: 11.77 | G110: 0 | H110: 2956.34 | I110: 2025-11 | J110: High confidence | K110: 6 | L110: 18 Nov Northen Beaches Denta DEE WHY AUS | Card xx0018 | Value Date 14/11/2025 11.77 2,956.34 CR
A111: 45979 | B111: Subway Kent 24 Market StrAU | D111: Dining & Coffee | E111: -6 | F111: 6 | G111: 0 | H111: 2950.34 | I111: 2025-11 | J111: High confidence | K111: 7 | L111: 18 Nov Subway Kent 24 Market StrAU 6.00 2,950.34 CR
A112: 45979 | B112: SMP*Hero Sushi Dee Why Dee Why02 | D112: Dining & Coffee | E112: -5.05 | F112: 5.05 | G112: 0 | H112: 2945.29 | I112: 2025-11 | J112: High confidence | K112: 7 | L112: 18 Nov SMP*Hero Sushi Dee Why Dee Why02 AU 5.05 2,945.29 CR
A113: 45980 | B113: Fast Transfer From AMAZON COMMERCIAL | C113: Salary NOVEMBER 2025 | PDY003326296642 | D113: Transfer In | E113: 0.01 | F113: 0 | G113: 0.01 | H113: 2945.3 | I113: 2025-11 | J113: High confidence | K113: 7 | L113: 19 Nov Fast Transfer From AMAZON COMMERCIAL SER | Salary NOVEMBER 2025 | PDY003326296642 0.01 2,945.30 CR
A114: 45980 | B114: TRANSPORTFORNSW TAP SYDNEY AUS | C114: Card xx0018 | Value Date 17/11/2025 | D114: Transport | E114: -8.06 | F114: 8.06 | G114: 0 | H114: 2937.24 | I114: 2025-11 | J114: High confidence | K114: 7 | L114: 19 Nov TRANSPORTFORNSW TAP SYDNEY AUS | Card xx0018 | Value Date 17/11/2025 8.06 2,937.24 CR
A115: 45980 | B115: SUSHI N PLUS PTY LTD SYDNEY AUS | C115: Card xx0018 | Value Date 17/11/2025 | D115: Dining & Coffee | E115: -8.1 | F115: 8.1 | G115: 0 | H115: 2929.14 | I115: 2025-11 | J115: High confidence | K115: 7 | L115: 19 Nov SUSHI N PLUS PTY LTD SYDNEY AUS | Card xx0018 | Value Date 17/11/2025 8.10 2,929.14 CR
A116: 45980 | B116: MARGOT ESPRESSO SYDNEY NS AUS | C116: Card xx0018 | Value Date 17/11/2025 | D116: Dining & Coffee | E116: -4.08 | F116: 4.08 | G116: 0 | H116: 2925.06 | I116: 2025-11 | J116: High confidence | K116: 7 | L116: 19 Nov MARGOT ESPRESSO SYDNEY NS AUS | =àXOÌ4) | Card xx0018 | Value Date 17/11/2025 4.08 2,925.06 CR
A117: 45980 | B117: SQ *SACREBLEU | CANELE dee why AU | D117: Dining & Coffee | E117: -9.44 | F117: 9.44 | G117: 0 | H117: 2915.62 | I117: 2025-11 | J117: High confidence | K117: 7 | L117: 19 Nov SQ *SACREBLEU | CANELE dee why AU 9.44 2,915.62 CR
A118: 45980 | B118: SQ *T TOTALER Sydney AU | D118: Dining & Coffee | E118: -9.65 | F118: 9.65 | G118: 0 | H118: 2905.97 | I118: 2025-11 | J118: High confidence | K118: 7 | L118: 19 Nov SQ *T TOTALER Sydney AU 9.65 2,905.97 CR
A119: 45980 | B119: Subway Dee Why 7 Oaks AvenueAU | D119: Dining & Coffee | E119: -2.95 | F119: 2.95 | G119: 0 | H119: 2903.02 | I119: 2025-11 | J119: High confidence | K119: 7 | L119: 19 Nov Subway Dee Why 7 Oaks AvenueAU 2.95 2,903.02 CR
A120: 45980 | B120: Direct Debit 507156 MBAUDPayments | C120: AMBITIONS_TRmCbip5 | D120: Fitness & Memberships | E120: -68 | F120: 68 | G120: 0 | H120: 2835.02 | I120: 2025-11 | J120: High confidence | K120: 7 | L120: 19 Nov Direct Debit 507156 MBAUDPayments | AMBITIONS_TRmCbip5 68.00 2,835.02 CR
A121: 45981 | B121: DEFT REAL ESTATE NetBank BPAY 4481 | C121: 0053436473 Rent may 9 to 23 | D121: Housing - Rent | E121: -1700 | F121: 1700 | G121: 0 | H121: 1135.02 | I121: 2025-11 | J121: High confidence | K121: 7 | L121: 20 Nov DEFT REAL ESTATE NetBank BPAY 4481 | 0053436473 Rent may 9 to 23 1,700.00 1,135.02 CR
A122: 45981 | B122: SQ *Y'NO DY Dee Why AU | D122: Other | E122: -4.5 | F122: 4.5 | G122: 0 | H122: 1130.52 | I122: 2025-11 | J122: High confidence | K122: 7 | L122: 20 Nov SQ *Y'NO DY Dee Why AU 4.50 1,130.52 CR
A123: 45982 | B123: TIYEB STORE PTY LTD SYDNEY NS AUS | C123: Card xx0018 | Value Date 19/11/2025 | D123: Groceries | E123: -5.04 | F123: 5.04 | G123: 0 | H123: 1125.48 | I123: 2025-11 | J123: High confidence | K123: 7 | L123: 21 Nov TIYEB STORE PTY LTD SYDNEY NS AUS | Card xx0018 | V06.00.37 | Value Date 19/11/2025 5.04 1,125.48 CR
...

Sheet Monthly Summary
A1: Month | B1: Recurring Direct Credit (AUD) | C1: Refunds / Other Income (AUD) | D1: Transfer In (AUD) | E1: Spending excl. Transfer Out (AUD) | F1: Transfer Out (AUD) | G1: Net Cash Flow (AUD)
A2: 2025-11 | B2: =SUMIFS(Transactions!$G$2:$G$201,Transactions!$I$2:$I$201,$A2,Transactions!$D$2:$D$201,"Income - Recurring Direct Credit") -> 0 | C2: =SUMIFS(Transactions!$G$2:$G$201,Transactions!$I$2:$I$201,$A2,Transactions!$D$2:$D$201,"Income - Refund/Reimbursement")+SUMIFS(Transactions!$G$2:$G$201,Transactions!$I$2:$I$201,$A2,Transactions!$D$2:$D$201,"Income - Other Credit") -> 0 | D2: =SUMIFS(Transactions!$G$2:$G$201,Transactions!$I$2:$I$201,$A2,Transactions!$D$2:$D$201,"Transfer In") -> 0 | E2: =SUMIFS(Transactions!$F$2:$F$201,Transactions!$I$2:$I$201,$A2)-SUMIFS(Transactions!$F$2:$F$201,Transactions!$I$2:$I$201,$A2,Transactions!$D$2:$D$201,"Transfer Out") -> 0 | F2: =SUMIFS(Transactions!$F$2:$F$201,Transactions!$I$2:$I$201,$A2,Transactions!$D$2:$D$201,"Transfer Out") -> 0 | G2: =B2+C2+D2-E2-F2 -> 0
A3: 2025-12 | B3: =SUMIFS(Transactions!$G$2:$G$201,Transactions!$I$2:$I$201,$A3,Transactions!$D$2:$D$201,"Income - Recurring Direct Credit") -> 0 | C3: =SUMIFS(Transactions!$G$2:$G$201,Transactions!$I$2:$I$201,$A3,Transactions!$D$2:$D$201,"Income - Refund/Reimbursement")+SUMIFS(Transactions!$G$2:$G$201,Transactions!$I$2:$I$201,$A3,Transactions!$D$2:$D$201,"Income - Other Credit") -> 0 | D3: =SUMIFS(Transactions!$G$2:$G$201,Transactions!$I$2:$I$201,$A3,Transactions!$D$2:$D$201,"Transfer In") -> 0 | E3: =SUMIFS(Transactions!$F$2:$F$201,Transactions!$I$2:$I$201,$A3)-SUMIFS(Transactions!$F$2:$F$201,Transactions!$I$2:$I$201,$A3,Transactions!$D$2:$D$201,"Transfer Out") -> 0 | F3: =SUMIFS(Transactions!$F$2:$F$201,Transactions!$I$2:$I$201,$A3,Transactions!$D$2:$D$201,"Transfer Out") -> 0 | G3: =B3+C3+D3-E3-F3 -> 0

Sheet Budget
A1: Suggested Monthly Budget
A2: Recurring-income baseline | B2: =MEDIAN('Monthly Summary'!B2) -> 0
A4: Category | B4: 2025-11 | C4: Average | D4: Suggested Cap | E4: Cap vs Avg | F4: Comment
A5: Housing - Rent | B5: =SUMIFS(Transactions!$F$2:$F$201,Transactions!$I$2:$I$201,"2025-11",Transactions!$D$2:$D$201,$A5) -> 0 | C5: =AVERAGE(B5:B5) -> 0 | D5: 3683 | E5: =D5-C5 -> 0 | F5: Fortnightly $1,700 normalized to 26 payments / 12 months.
A6: Groceries | B6: =SUMIFS(Transactions!$F$2:$F$201,Transactions!$I$2:$I$201,"2025-11",Transactions!$D$2:$D$201,$A6) -> 0 | C6: =AVERAGE(B6:B6) -> 0 | D6: 550 | E6: =D6-C6 -> 0 | F6: Baseline allowance for supermarket / grocery spending.
A7: Dining & Coffee | B7: =SUMIFS(Transactions!$F$2:$F$201,Transactions!$I$2:$I$201,"2025-11",Transactions!$D$2:$D$201,$A7) -> 0 | C7: =AVERAGE(B7:B7) -> 0 | D7: 650 | E7: =D7-C7 -> 0 | F7: A controllable category; target is below the observed run-rate.
A8: Utilities & Phone | B8: =SUMIFS(Transactions!$F$2:$F$201,Transactions!$I$2:$I$201,"2025-11",Transactions!$D$2:$D$201,$A8) -> 0 | C8: =AVERAGE(B8:B8) -> 0 | D8: 350 | E8: =D8-C8 -> 0 | F8: Smooths irregular billing months.
A9: Transport | B9: =SUMIFS(Transactions!$F$2:$F$201,Transactions!$I$2:$I$201,"2025-11",Transactions!$D$2:$D$201,$A9) -> 0 | C9: =AVERAGE(B9:B9) -> 0 | D9: 450 | E9: =D9-C9 -> 0 | F9: Allows for Opal/Uber/fuel/taxis.
A10: Fitness & Memberships | B10: =SUMIFS(Transactions!$F$2:$F$201,Transactions!$I$2:$I$201,"2025-11",Transactions!$D$2:$D$201,$A10) -> 0 | C10: =AVERAGE(B10:B10) -> 0 | D10: 354 | E10: =D10-C10 -> 0 | F10: Approximately current recurring run-rate.
A11: Health & Pharmacy | B11: =SUMIFS(Transactions!$F$2:$F$201,Transactions!$I$2:$I$201,"2025-11",Transactions!$D$2:$D$201,$A11) -> 0 | C11: =AVERAGE(B11:B11) -> 0 | D11: 400 | E11: =D11-C11 -> 0 | F11: Buffer for pharmacy/medical variability.
A12: Shopping | B12: =SUMIFS(Transactions!$F$2:$F$201,Transactions!$I$2:$I$201,"2025-11",Transactions!$D$2:$D$201,$A12) -> 0 | C12: =AVERAGE(B12:B12) -> 0 | D12: 600 | E12: =D12-C12 -> 0 | F12: Main discretionary reduction target.
A13: Beauty & Personal Care | B13: =SUMIFS(Transactions!$F$2:$F$201,Transactions!$I$2:$I$201,"2025-11",Transactions!$D$2:$D$201,$A13) -> 0 | C13: =AVERAGE(B13:B13) -> 0 | D13: 150 | E13: =D13-C13 -> 0 | F13: Use as a monthly cap / sinking fund.
A14: Home & Household | B14: =SUMIFS(Transactions!$F$2:$F$201,Transactions!$I$2:$I$201,"2025-11",Transactions!$D$2:$D$201,$A14) -> 0 | C14: =AVERAGE(B14:B14) -> 0 | D14: 250 | E14: =D14-C14 -> 0 | F14: Sinking fund for irregular household purchases.
A15: Entertainment & Experiences | B15: =SUMIFS(Transactions!$F$2:$F$201,Transactions!$I$2:$I$201,"2025-11",Transactions!$D$2:$D$201,$A15) -> 0 | C15: =AVERAGE(B15:B15) -> 0 | D15: 100 | E15: =D15-C15 -> 0 | F15: Monthly leisure allowance.
A16: Subscriptions & Donations | B16: =SUMIFS(Transactions!$F$2:$F$201,Transactions!$I$2:$I$201,"2025-11",Transactions!$D$2:$D$201,$A16) -> 0 | C16: =AVERAGE(B16:B16) -> 0 | D16: 15 | E16: =D16-C16 -> 0 | F16: Recurring subscriptions/donations.
... A21: Other | B21: =SUMIFS(Transactions!$F$2:$F$201,Transactions!$I$2:$I$201,"2025-11",Transactions!$D$2:$D$201,$A21) -> 0 | C21: =AVERAGE(B21:B21) -> 0 | D21: 250 | E21: =D21-C21 -> 0 | F21: Buffer for merchants not yet confidently categorized.
A22: TOTAL MONTHLY SPEND | B22: =SUM(B5:B21) -> 0 | C22: =SUM(C5:C21) -> 0 | D22: =SUM(D5:D21) -> 0 | E22: =SUM(E5:E21) -> 0
A25: Budget outcome
A26: Income baseline | B26: =$B$2 -> 0
A27: Suggested monthly spend | B27: =D22 -> 0
A28: Implied monthly savings | B28: =B26-B27 -> 0
A29: Savings rate | B29: =IFERROR(B28/B26,0) -> 0

Sheet Review
A1: Date | B1: Description | C1: Category | D1: Amount | E1: Parse Status | F1: Page | G1: Why shown
A2: 45962 | B2: HAWAIIAN1734212522763 PARIS FR | C2: Other | D2: -35.16 | E2: High confidence | F2: 1 | G2: Uncategorized merchant
A3: 45962 | B3: THE TASTE OF ASIAN PTY MASCOT AUS | C3: Other | D3: -20 | E3: High confidence | F3: 1 | G3: Uncategorized merchant
A4: 45962 | B4: International Transaction Fee | C4: Bank Fees | D4: -18.64 | E4: Amount mismatch: columns -0.63, balance delta -18.64; used balance | F4: 1 | G4: Parser reconstruction / mismatch
A5: 45962 | B5: Liv Eat Mascot NS AUS | C5: Other | D5: -6.09 | E5: High confidence | F5: 1 | G5: Uncategorized merchant
A6: 45965 | B6: KEN'S MARKET 75-116 SEATTLE WA | C6: Other | D6: -4.21 | E6: High confidence | F6: 2 | G6: Uncategorized merchant
A7: 45965 | B7: AIRBNB * HMMCN3N8CD LONDON GB | C7: Other | D7: -144.88 | E7: High confidence | F7: 2 | G7: Uncategorized merchant
A8: 45965 | B8: International Transaction Fee | C8: Bank Fees | D8: -32.01 | E8: Amount mismatch: columns -0.84, balance delta -32.01; used balance | F8: 2 | G8: Parser reconstruction / mismatch
A9: 45965 | B9: International Transaction Fee | C9: Bank Fees | D9: -11.36 | E9: Amount mismatch: columns -0.38, balance delta -11.36; used balance | F9: 2 | G9: Parser reconstruction / mismatch
A10: 45965 | B10: SQ *PAGES & PAGES HONO Honolulu | C10: Other | D10: -7.64 | E10: High confidence | F10: 2 | G10: Uncategorized merchant
A11: 45966 | B11: SQ *SIFF CINEMA DOWNTO Seattle WA | C11: Other | D11: -15.31 | E11: High confidence | F11: 2 | G11: Uncategorized merchant
A12: 45966 | B12: SP MUTO.ARTONTHETABLE SEATTLE | C12: Other | D12: -159.35 | E12: High confidence | F12: 3 | G12: Uncategorized merchant
A13: 45966 | B13: XING FU TANG SEATTLE WA USA | C13: Other | D13: -14.16 | E13: High confidence | F13: 3 | G13: Uncategorized merchant
... A67: 45994 | B67: KUDOBOARD DENVER CO USA | C67: Other | D67: -15.72 | E67: High confidence | F67: 10 | G67: Uncategorized merchant

Sheet Assumptions
A1: Parsing & budgeting assumptions
A3: Source | B3: Statement.pdf | C3: Parser | D3: PyMuPDF text + coordinate columns; no OCR / no network
A4: Statement period | B4: 2025-11-01 to 2025-12-04 | C4: Complete budget months | D4: 2025-11
A5: Opening balance | B5: 7659.32 | C5: Closing balance | D5: 5034.38
A6: Transactions | B6: 200 | C6: Reconstructed / mismatched rows | D6: 14
A7: Reconciliation | B7: Every amount is checked against the running balance. | C7: Failure mode | D7: Workbook is not written if the statement does not reconcile.
A8: Income baseline | B8: Direct Credit / salary / wages are recurring income unless identified as refunds. | C8: Transfers | D8: Transfers and cash deposits are kept separate from recurring income.
A9: Categories | B9: Merchant categories are heuristic and editable in Transactions column D. | C9: Permanent rules | D9: Edit CATEGORY_RULES near the top of this script.
A10: Budget | B10: Suggested caps are editable near the top of this script. | C10: Partial months | D10: Only complete calendar months are used when the statement period allows it.

Sheet Dashboard
A1: Personal Budget Dashboard
A3: Period | B3: 2025-11-01 to 2025-12-04 | D3: Recurring income baseline | E3: =Budget!B2 -> 0
A4: Transactions | B4: 200 | D4: Suggested monthly budget | E4: =Budget!D22 -> 0
A5: Opening balance | B5: 7659.32 | D5: Implied monthly savings | E5: =E3-E4 -> 0
A6: Closing balance | B6: 5034.38 | D6: Implied savings rate | E6: =IFERROR(E5/E3,0) -> 0
A7: Rows needing parser reconstruction | B7: 14
