Workbook

Sheet Dashboard
A1: Personal Budget Dashboard
A3: Period | B3: 2026-06-01 to 2026-09-08 | D3: Recurring income baseline | E3: 10281.64
A4: Transactions | B4: 787 | D4: Average core spend | E4: 9406.9267
A5: Opening balance | B5: 20478.71 | D5: Average irregular spend | E5: 1158.9433
A6: Closing balance | B6: 25462.14 | D6: Average unknown spend | E6: 1033.27
A7: Merchants to review | B7: 134 | D7: Suggested monthly budget | E7: 8272
D8: Implied savings at cap | E8: 2009.64

Sheet Transactions
A1: Date | B1: Description | C1: Details | D1: Merchant | E1: Category | F1: Budget Character | G1: Rule Status | H1: Rule Match | I1: Amount (AUD) | J1: Debit (AUD) | K1: Credit (AUD) | L1: Statement Balance (AUD) | M1: Month | N1: Parse Status | O1: Source Page | P1: Raw PDF text
A2: 46174 | B2: SQ *KAHII Sydney AU | D2: Kahii | E2: Dining & Coffee | F2: Discretionary | G2: suggested | H2: contains:KAHII | I2: -7.1 | J2: 7.1 | K2: 0 | L2: 20471.61 | M2: 2026-06 | N2: High confidence | O2: 1 | P2: 01 Jun 2026 SQ *KAHII Sydney AU -$7.10 $20,471.61
A3: 46174 | B3: Direct Credit 158824 AMAZON COMMERCIA | C3: FCS003830996572 | D3: Direct Credit 158824 AMAZON COMMERCIA | E3: Income - Recurring Direct Credit | F3: Income | G3: system | I3: 403.5 | J3: 0 | K3: 403.5 | L3: 20875.11 | M3: 2026-06 | N3: High confidence | O3: 1 | P3: 01 Jun 2026 Direct Credit 158824 AMAZON COMMERCIA $403.50 $20,875.11 | FCS003830996572
A4: 46174 | B4: Direct Debit 012495 GU HEALTH D/DBT | C4: 29497443 | D4: Direct Debit 012495 GU HEALTH D/DBT | E4: Health & Pharmacy | F4: Essential | G4: fallback | H4: fallback:gu health d/dbt | I4: -139.08 | J4: 139.08 | K4: 0 | L4: 20736.03 | M4: 2026-06 | N4: High confidence | O4: 1 | P4: 01 Jun 2026 Direct Debit 012495 GU HEALTH D/DBT -$139.08 $20,736.03 | 29497443
A5: 46175 | B5: REBEL BROOKVALE BROOKVALE NS AUS | C5: Card xx2810 | Value Date: 30/05/2026 | D5: Rebel | E5: Shopping | F5: Discretionary | G5: confirmed | H5: contains:REBEL | I5: -67.99 | J5: 67.99 | K5: 0 | L5: 20668.04 | M5: 2026-06 | N5: High confidence | O5: 1 | P5: 02 Jun 2026 REBEL BROOKVALE BROOKVALE NS AUS -$67.99 $20,668.04 | Card xx2810 | Value Date: 30/05/2026
A6: 46175 | B6: The Vicars Daughters Collaroy AU AUS | C6: Card xx2810 | Value Date: 31/05/2026 | D6: The Vicars Daughters Collaroy | E6: Other | F6: Unknown | G6: unmatched | I6: -22.36 | J6: 22.36 | K6: 0 | L6: 20645.68 | M6: 2026-06 | N6: High confidence | O6: 1 | P6: 02 Jun 2026 The Vicars Daughters Collaroy AU AUS -$22.36 $20,645.68 | Card xx2810 | Value Date: 31/05/2026
A7: 46175 | B7: SEA VIEW CAFE & RESTA Dee Why NS AUS | C7: Card xx2810 | Value Date: 31/05/2026 | D7: SEA VIEW CAFE & RESTA Dee Why | E7: Dining & Coffee | F7: Discretionary | G7: fallback | H7: fallback:cafe | I7: -10.49 | J7: 10.49 | K7: 0 | L7: 20635.19 | M7: 2026-06 | N7: High confidence | O7: 1 | P7: 02 Jun 2026 SEA VIEW CAFE & RESTA Dee Why NS AUS -$10.49 $20,635.19 | Card xx2810 | Value Date: 31/05/2026
A8: 46175 | B8: LSP*Corretto Dee Why Dee Why AU AUS | C8: Card xx2810 | Value Date: 30/05/2026 | D8: Corretto Dee Why Dee Why | E8: Dining & Coffee | F8: Discretionary | G8: fallback | H8: fallback:corretto | I8: -51.25 | J8: 51.25 | K8: 0 | L8: 20583.94 | M8: 2026-06 | N8: High confidence | O8: 1 | P8: 02 Jun 2026 LSP*Corretto Dee Why Dee Why AU AUS -$51.25 $20,583.94 | Card xx2810 | Value Date: 30/05/2026
A9: 46175 | B9: COLES 0784 DEE WHY NS AUS | C9: Card xx0018 | Value Date: 31/05/2026 | D9: COLES 0784 DEE WHY | E9: Groceries | F9: Essential | G9: fallback | H9: fallback:coles | I9: -81.76 | J9: 81.76 | K9: 0 | L9: 20502.18 | M9: 2026-06 | N9: High confidence | O9: 1 | P9: 02 Jun 2026 COLES 0784 DEE WHY NS AUS -$81.76 $20,502.18 | Card xx0018 | Value Date: 31/05/2026
A10: 46175 | B10: W RETAIL GROUP PTY LTD WARRINGAH AUS | C10: Card xx0018 | Value Date: 30/05/2026 | D10: W RETAIL GROUP PTY LTD WARRINGAH | E10: Groceries | F10: Essential | G10: fallback | H10: fallback:w retail group | I10: -53.43 | J10: 53.43 | K10: 0 | L10: 20448.75 | M10: 2026-06 | N10: High confidence | O10: 1 | P10: 02 Jun 2026 W RETAIL GROUP PTY LTD WARRINGAH AUS -$53.43 $20,448.75 | Card xx0018 | Value Date: 30/05/2026
A11: 46175 | B11: GUZMAN Y GOMEZ 0291910900 AU AUS | C11: Card xx0018 | Value Date: 30/05/2026 | D11: GUZMAN Y GOMEZ | E11: Dining & Coffee | F11: Discretionary | G11: fallback | H11: fallback:guzman | I11: -16.9 | J11: 16.9 | K11: 0 | L11: 20431.85 | M11: 2026-06 | N11: High confidence | O11: 1 | P11: 02 Jun 2026 GUZMAN Y GOMEZ 0291910900 AU AUS -$16.90 $20,431.85 | Card xx0018 | Value Date: 30/05/2026
A12: 46175 | B12: COLES 0897 BROOKVALE NS AUS | C12: Card xx0018 | Value Date: 30/05/2026 | D12: COLES 0897 BROOKVALE | E12: Groceries | F12: Essential | G12: fallback | H12: fallback:coles | I12: -34.3 | J12: 34.3 | K12: 0 | L12: 20397.55 | M12: 2026-06 | N12: High confidence | O12: 1 | P12: 02 Jun 2026 COLES 0897 BROOKVALE NS AUS -$34.30 $20,397.55 | Card xx0018 | Value Date: 30/05/2026
A13: 46175 | B13: TRANSPORTFORNSW TAP SYDNEY AUS | C13: Card xx0018 | Value Date: 29/05/2026 | D13: Transport for NSW | E13: Transport | F13: Essential | G13: confirmed | H13: contains:TRANSPORTFORNSW | I13: -5.77 | J13: 5.77 | K13: 0 | L13: 20391.78 | M13: 2026-06 | N13: High confidence | O13: 2 | P13: 02 Jun 2026 TRANSPORTFORNSW TAP SYDNEY AUS -$5.77 $20,391.78 | Card xx0018 | Value Date: 29/05/2026
A14: 46175 | B14: SQ *KAHII Sydney AU | D14: Kahii | E14: Dining & Coffee | F14: Discretionary | G14: suggested | H14: contains:KAHII | I14: -7.1 | J14: 7.1 | K14: 0 | L14: 20384.68 | M14: 2026-06 | N14: High confidence | O14: 2 | P14: 02 Jun 2026 SQ *KAHII Sydney AU -$7.10 $20,384.68
A15: 46176 | B15: AMZNPRIMEA* AMZNPRIMEA SYDNEY SOUTH NS AUS | C15: Card xx6220 | Value Date: 01/06/2026 | D15: Amazon Prime | E15: Subscriptions & Donations | F15: Discretionary | G15: confirmed | H15: contains:AMZNPRIMEA | I15: -79 | J15: 79 | K15: 0 | L15: 20305.68 | M15: 2026-06 | N15: High confidence | O15: 2 | P15: 03 Jun 2026 AMZNPRIMEA* AMZNPRIMEA SYDNEY SOUTH NS -$79.00 $20,305.68 | AUS | Card xx6220 | Value Date: 01/06/2026
A16: 46176 | B16: BITE* BBDEE WHY SANCROX NS AUS | C16: Card xx2810 | Value Date: 01/06/2026 | D16: BITE* BBDEE WHY SANCROX | E16: Dining & Coffee | F16: Discretionary | G16: fallback | H16: fallback:bite* | I16: -27.78 | J16: 27.78 | K16: 0 | L16: 20277.9 | M16: 2026-06 | N16: High confidence | O16: 2 | P16: 03 Jun 2026 BITE* BBDEE WHY SANCROX NS AUS -$27.78 $20,277.90 | Card xx2810 | Value Date: 01/06/2026
A17: 46176 | B17: TRANSPORTFORNSW TAP SYDNEY AUS | C17: Card xx0018 | Value Date: 01/06/2026 | D17: Transport for NSW | E17: Transport | F17: Essential | G17: confirmed | H17: contains:TRANSPORTFORNSW | I17: -2.31 | J17: 2.31 | K17: 0 | L17: 20275.59 | M17: 2026-06 | N17: High confidence | O17: 2 | P17: 03 Jun 2026 TRANSPORTFORNSW TAP SYDNEY AUS -$2.31 $20,275.59 | Card xx0018 | Value Date: 01/06/2026
A18: 46176 | B18: VIET VIBE BROOKVALE AUS | C18: Card xx0018 | Value Date: 30/05/2026 | D18: VIET VIBE BROOKVALE | E18: Dining & Coffee | F18: Discretionary | G18: fallback | H18: fallback:viet vibe | I18: -22.33 | J18: 22.33 | K18: 0 | L18: 20253.26 | M18: 2026-06 | N18: High confidence | O18: 2 | P18: 03 Jun 2026 VIET VIBE BROOKVALE AUS -$22.33 $20,253.26 | Card xx0018 | Value Date: 30/05/2026
A19: 46176 | B19: MAO SHENG ASIAN SUPE DEE WHY AUS | C19: Card xx0018 | Value Date: 30/05/2026 | D19: MAO SHENG ASIAN SUPE DEE WHY | E19: Groceries | F19: Essential | G19: fallback | H19: fallback:mao sheng | I19: -5.4 | J19: 5.4 | K19: 0 | L19: 20247.86 | M19: 2026-06 | N19: High confidence | O19: 2 | P19: 03 Jun 2026 MAO SHENG ASIAN SUPE DEE WHY AUS -$5.40 $20,247.86 | Card xx0018 | Value Date: 30/05/2026
A20: 46176 | B20: asos.com Melbourne AUS | C20: Card xx0018 | Value Date: 01/06/2026 | D20: ASOS | E20: Shopping | F20: Discretionary | G20: confirmed | H20: contains:ASOS | I20: -123.99 | J20: 123.99 | K20: 0 | L20: 20123.87 | M20: 2026-06 | N20: High confidence | O20: 2 | P20: 03 Jun 2026 asos.com Melbourne AUS -$123.99 $20,123.87 | Card xx0018 | Value Date: 01/06/2026
A21: 46176 | B21: SQ *SALUMERIE - SYDNEY Sydney AU | D21: SALUMERIE - SYDNEY Sydney | E21: Dining & Coffee | F21: Discretionary | G21: fallback | H21: fallback:salumerie | I21: -6.6 | J21: 6.6 | K21: 0 | L21: 20117.27 | M21: 2026-06 | N21: High confidence | O21: 2 | P21: 03 Jun 2026 SQ *SALUMERIE - SYDNEY Sydney AU -$6.60 $20,117.27
A22: 46176 | B22: SQ *KAHII Sydney AU | D22: Kahii | E22: Dining & Coffee | F22: Discretionary | G22: suggested | H22: contains:KAHII | I22: -7.1 | J22: 7.1 | K22: 0 | L22: 20110.17 | M22: 2026-06 | N22: High confidence | O22: 2 | P22: 03 Jun 2026 SQ *KAHII Sydney AU -$7.10 $20,110.17
A23: 46176 | B23: COLES 0784 DEE WHY AU | D23: COLES 0784 DEE WHY | E23: Groceries | F23: Essential | G23: fallback | H23: fallback:coles | I23: -23.16 | J23: 23.16 | K23: 0 | L23: 20087.01 | M23: 2026-06 | N23: High confidence | O23: 2 | P23: 03 Jun 2026 COLES 0784 DEE WHY AU -$23.16 $20,087.01
A24: 46176 | B24: Transfer To Jetstar Airways Pty Ltd - $1 | C24: PayID Email from CommBank App | Booking Reference IT3ZJX | D24: Transfer To Jetstar Airways Pty Ltd - $1 | E24: Transfer Out | F24: Transfer | G24: system | I24: -1104 | J24: 1104 | K24: 0 | L24: 18983.01 | M24: 2026-06 | N24: High confidence | O24: 2 | P24: 03 Jun 2026 Transfer To Jetstar Airways Pty Ltd - $1 -$1,104.00 $18,983.01 | PayID Email from CommBank App | Booking Reference IT3ZJX
A25: 46176 | B25: Direct Debit 507156 MBAUDPayments | C25: AMBITIONS_UdCSdbn6 | D25: Direct Debit 507156 MBAUDPayments | E25: Fitness & Memberships | F25: Discretionary | G25: fallback | H25: fallback:mbaudpayments | I25: -68 | J25: 68 | K25: 0 | L25: 18915.01 | M25: 2026-06 | N25: High confidence | O25: 2 | P25: 03 Jun 2026 Direct Debit 507156 MBAUDPayments -$68.00 $18,915.01 | AMBITIONS_UdCSdbn6
A26: 46177 | B26: ENERGYAUSTRALIA PTY LT MELBOURNE AUS | C26: Card xx6220 | Value Date: 03/06/2026 | D26: ENERGYAUSTRALIA PTY LT MELBOURNE | E26: Utilities & Phone | F26: Essential | G26: fallback | H26: fallback:energyaustralia | I26: -380.28 | J26: 380.28 | K26: 0 | L26: 18534.73 | M26: 2026-06 | N26: High confidence | O26: 2 | P26: 04 Jun 2026 ENERGYAUSTRALIA PTY LT MELBOURNE AUS -$380.28 $18,534.73 | Card xx6220 | Value Date: 03/06/2026
A27: 46177 | B27: TRANSPORTFORNSW TAP SYDNEY AUS | C27: Card xx0018 | Value Date: 02/06/2026 | D27: Transport for NSW | E27: Transport | F27: Essential | G27: confirmed | H27: contains:TRANSPORTFORNSW | I27: -5.77 | J27: 5.77 | K27: 0 | L27: 18528.96 | M27: 2026-06 | N27: High confidence | O27: 2 | P27: 04 Jun 2026 TRANSPORTFORNSW TAP SYDNEY AUS -$5.77 $18,528.96 | Card xx0018 | Value Date: 02/06/2026
A28: 46177 | B28: FLYING HAT SYDNEY AUS | C28: Card xx0018 | Value Date: 02/06/2026 | D28: Flying Hat | E28: Dining & Coffee | F28: Discretionary | G28: suggested | H28: contains:FLYING HAT | I28: -6.07 | J28: 6.07 | K28: 0 | L28: 18522.89 | M28: 2026-06 | N28: High confidence | O28: 2 | P28: 04 Jun 2026 FLYING HAT SYDNEY AUS -$6.07 $18,522.89 | Card xx0018 | Value Date: 02/06/2026
A29: 46177 | B29: 100 CLARENCE PTY LTD SYDNEY AUS | C29: Card xx0018 | Value Date: 01/06/2026 | D29: 100 CLARENCE PTY LTD SYDNEY | E29: Other | F29: Unknown | G29: unmatched | I29: -6.59 | J29: 6.59 | K29: 0 | L29: 18516.3 | M29: 2026-06 | N29: High confidence | O29: 2 | P29: 04 Jun 2026 100 CLARENCE PTY LTD SYDNEY AUS -$6.59 $18,516.30 | Card xx0018 | Value Date: 01/06/2026
A30: 46177 | B30: HUNGRYPANDA AU PRAHRAN VI AUS | C30: Card xx0018 | Value Date: 02/06/2026 | D30: HungryPanda | E30: Dining & Coffee | F30: Discretionary | G30: confirmed | H30: contains:HUNGRYPANDA | I30: -14.03 | J30: 14.03 | K30: 0 | L30: 18502.27 | M30: 2026-06 | N30: High confidence | O30: 3 | P30: 04 Jun 2026 HUNGRYPANDA AU PRAHRAN VI AUS -$14.03 $18,502.27 | Card xx0018 | Value Date: 02/06/2026
A31: 46177 | B31: DEFT REAL ESTATE NetBank BPAY 4481 0053436473 Rent may 9 to 23 | D31: DEFT REAL ESTATE NetBank BPAY 4481 Rent may 9 to 23 | E31: Housing - Rent | F31: Essential | G31: fallback | H31: fallback:deft real estate | I31: -1720 | J31: 1720 | K31: 0 | L31: 16782.27 | M31: 2026-06 | N31: High confidence | O31: 3 | P31: 04 Jun 2026 DEFT REAL ESTATE NetBank BPAY 4481 -$1,720.00 $16,782.27 | 0053436473 Rent may 9 to 23
A32: 46177 | B32: SQ *SKITTLE LANE Sydney AU | D32: SKITTLE LANE Sydney | E32: Dining & Coffee | F32: Discretionary | G32: fallback | H32: fallback:skittle lane | I32: -5.58 | J32: 5.58 | K32: 0 | L32: 16776.69 | M32: 2026-06 | N32: High confidence | O32: 3 | P32: 04 Jun 2026 SQ *SKITTLE LANE Sydney AU -$5.58 $16,776.69
A33: 46177 | B33: SQ *MADAME LYNN Pyrmont AU | D33: MADAME LYNN Pyrmont | E33: Other | F33: Unknown | G33: unmatched | I33: -11.18 | J33: 11.18 | K33: 0 | L33: 16765.51 | M33: 2026-06 | N33: High confidence | O33: 3 | P33: 04 Jun 2026 SQ *MADAME LYNN Pyrmont AU -$11.18 $16,765.51
A34: 46177 | B34: SQ *LETAO SYDNEY Sydney AU | D34: LETAO SYDNEY Sydney | E34: Other | F34: Unknown | G34: unmatched | I34: -7.09 | J34: 7.09 | K34: 0 | L34: 16758.42 | M34: 2026-06 | N34: High confidence | O34: 3 | P34: 04 Jun 2026 SQ *LETAO SYDNEY Sydney AU -$7.09 $16,758.42
A35: 46178 | B35: AMAZON AU RETAIL SYDNEY AUS | C35: Card xx6220 | Value Date: 01/06/2026 | D35: AMAZON RETAIL SYDNEY | E35: Shopping | F35: Discretionary | G35: fallback | H35: fallback:amazon au | I35: -36.1 | J35: 36.1 | K35: 0 | L35: 16722.32 | M35: 2026-06 | N35: High confidence | O35: 3 | P35: 05 Jun 2026 AMAZON AU RETAIL SYDNEY AUS -$36.10 $16,722.32 | Card xx6220 | Value Date: 01/06/2026
A36: 46178 | B36: BEAUTYFASCIA SHERIDAN WY USA | C36: Card xx0018 USD 49.00 | Value Date: 03/06/2026 | D36: BeautyFascia | E36: Beauty & Personal Care | F36: Discretionary | G36: confirmed | H36: contains:BEAUTYFASCIA | I36: -68.57 | J36: 68.57 | K36: 0 | L36: 16653.75 | M36: 2026-06 | N36: High confidence | O36: 3 | P36: 05 Jun 2026 BEAUTYFASCIA SHERIDAN WY USA -$68.57 $16,653.75 | Card xx0018 USD 49.00 | Value Date: 03/06/2026
A37: 46178 | B37: International Transaction Fee | C37: Value Date: 02/06/2026 | D37: International Transaction Fee | E37: Bank Fees | F37: Essential | G37: fallback | H37: fallback:international transaction fee | I37: -2.4 | J37: 2.4 | K37: 0 | L37: 16651.35 | M37: 2026-06 | N37: High confidence | O37: 3 | P37: 05 Jun 2026 International Transaction Fee -$2.40 $16,651.35 | Value Date: 02/06/2026
A38: 46178 | B38: SQ *PANINO PARADISO Sydney AU | D38: PANINO PARADISO Sydney | E38: Dining & Coffee | F38: Discretionary | G38: fallback | H38: fallback:panino paradiso | I38: -5.1 | J38: 5.1 | K38: 0 | L38: 16646.25 | M38: 2026-06 | N38: High confidence | O38: 3 | P38: 05 Jun 2026 SQ *PANINO PARADISO Sydney AU -$5.10 $16,646.25
A39: 46178 | B39: SQ *PANINO PARADISO Sydney AU | D39: PANINO PARADISO Sydney | E39: Dining & Coffee | F39: Discretionary | G39: fallback | H39: fallback:panino paradiso | I39: -6.11 | J39: 6.11 | K39: 0 | L39: 16640.14 | M39: 2026-06 | N39: High confidence | O39: 3 | P39: 05 Jun 2026 SQ *PANINO PARADISO Sydney AU -$6.11 $16,640.14
A40: 46178 | B40: SNSW*NSW Parks | D40: NSW National Parks | E40: Entertainment & Experiences | F40: Irregular | G40: confirmed | H40: contains:SNSW*NSW PARKS | I40: -34.85 | J40: 34.85 | K40: 0 | L40: 16605.29 | M40: 2026-06 | N40: High confidence | O40: 3 | P40: 05 Jun 2026 SNSW*NSW Parks -$34.85 $16,605.29
A41: 46178 | B41: MUJI RETAIL (AUSTRAL SYDNEY AU | D41: MUJI RETAIL (AUSTRAL SYDNEY | E41: Shopping | F41: Discretionary | G41: fallback | H41: fallback:muji retail | I41: -40.2 | J41: 40.2 | K41: 0 | L41: 16565.09 | M41: 2026-06 | N41: High confidence | O41: 3 | P41: 05 Jun 2026 MUJI RETAIL (AUSTRAL SYDNEY AU -$40.20 $16,565.09
A42: 46179 | B42: SQ *WINGMILL Dee Why NS AUS | C42: Card xx0018 | Value Date: 04/06/2026 | D42: WINGMILL Dee Why | E42: Dining & Coffee | F42: Discretionary | G42: fallback | H42: fallback:wingmill | I42: -45 | J42: 45 | K42: 0 | L42: 16520.09 | M42: 2026-06 | N42: High confidence | O42: 3 | P42: 06 Jun 2026 SQ *WINGMILL Dee Why NS AUS -$45.00 $16,520.09 | Card xx0018 | Value Date: 04/06/2026
A43: 46179 | B43: SQ *SACREBLEU ! CANELE dee why AU | D43: SACREBLEU ! CANELE dee why | E43: Dining & Coffee | F43: Discretionary | G43: fallback | H43: fallback:canele | I43: -47.48 | J43: 47.48 | K43: 0 | L43: 16472.61 | M43: 2026-06 | N43: High confidence | O43: 3 | P43: 06 Jun 2026 SQ *SACREBLEU ! CANELE dee why AU -$47.48 $16,472.61
A44: 46179 | B44: SQ *BUTTERBOX LONGREEF Wheeler Heigh AU | D44: BUTTERBOX LONGREEF Wheeler Heigh | E44: Other | F44: Unknown | G44: unmatched | I44: -6 | J44: 6 | K44: 0 | L44: 16466.61 | M44: 2026-06 | N44: High confidence | O44: 3 | P44: 06 Jun 2026 SQ *BUTTERBOX LONGREEF Wheeler Heigh AU -$6.00 $16,466.61
A45: 46179 | B45: The Burek Guy Dee Why Dee Why AU | D45: The Burek Guy Dee Why Dee Why | E45: Dining & Coffee | F45: Discretionary | G45: fallback | H45: fallback:burek | I45: -9.11 | J45: 9.11 | K45: 0 | L45: 16457.5 | M45: 2026-06 | N45: High confidence | O45: 3 | P45: 06 Jun 2026 The Burek Guy Dee Why Dee Why AU -$9.11 $16,457.50
A46: 46179 | B46: LS LIFELINE NORTHERN Balgowlah AU | D46: LIFELINE NORTHERN Balgowlah | E46: Other | F46: Unknown | G46: unmatched | I46: -8.05 | J46: 8.05 | K46: 0 | L46: 16449.45 | M46: 2026-06 | N46: High confidence | O46: 3 | P46: 06 Jun 2026 LS LIFELINE NORTHERN Balgowlah AU -$8.05 $16,449.45
A47: 46180 | B47: Transfer To O ARSLAN | C47: PayID Phone from CommBank App | Baklava | D47: Transfer To O ARSLAN | E47: Transfer Out | F47: Transfer | G47: system | I47: -10 | J47: 10 | K47: 0 | L47: 16439.45 | M47: 2026-06 | N47: High confidence | O47: 3 | P47: 07 Jun 2026 Transfer To O ARSLAN -$10.00 $16,439.45 | PayID Phone from CommBank App | Baklava
A48: 46180 | B48: SQ *GUSTO ON THE BEACH Dee Why AU | D48: GUSTO ON THE BEACH Dee Why | E48: Other | F48: Unknown | G48: unmatched | I48: -33.53 | J48: 33.53 | K48: 0 | L48: 16405.92 | M48: 2026-06 | N48: High confidence | O48: 3 | P48: 07 Jun 2026 SQ *GUSTO ON THE BEACH Dee Why AU -$33.53 $16,405.92
A49: 46180 | B49: COLES 0784 DEE WHY AU | D49: COLES 0784 DEE WHY | E49: Groceries | F49: Essential | G49: fallback | H49: fallback:coles | I49: -12.5 | J49: 12.5 | K49: 0 | L49: 16393.42 | M49: 2026-06 | N49: High confidence | O49: 3 | P49: 07 Jun 2026 COLES 0784 DEE WHY AU -$12.50 $16,393.42
A50: 46180 | B50: SQ *WINGMILL Dee Why AU | D50: WINGMILL Dee Why | E50: Dining & Coffee | F50: Discretionary | G50: fallback | H50: fallback:wingmill | I50: -61.05 | J50: 61.05 | K50: 0 | L50: 16332.37 | M50: 2026-06 | N50: High confidence | O50: 3 | P50: 07 Jun 2026 SQ *WINGMILL Dee Why AU -$61.05 $16,332.37
A51: 46180 | B51: SQ *WINGMILL Dee Why AU | D51: WINGMILL Dee Why | E51: Dining & Coffee | F51: Discretionary | G51: fallback | H51: fallback:wingmill | I51: -31.9 | J51: 31.9 | K51: 0 | L51: 16300.47 | M51: 2026-06 | N51: High confidence | O51: 3 | P51: 07 Jun 2026 SQ *WINGMILL Dee Why AU -$31.90 $16,300.47
A52: 46181 | B52: SQ *CASA FOCACCIA Dee Why AU | D52: CASA FOCACCIA Dee Why | E52: Other | F52: Unknown | G52: unmatched | I52: -22.35 | J52: 22.35 | K52: 0 | L52: 16278.12 | M52: 2026-06 | N52: High confidence | O52: 3 | P52: 08 Jun 2026 SQ *CASA FOCACCIA Dee Why AU -$22.35 $16,278.12
A53: 46181 | B53: SQ *DY LOCAL Dee Why AU | D53: DY LOCAL Dee Why | E53: Other | F53: Unknown | G53: unmatched | I53: -9.98 | J53: 9.98 | K53: 0 | L53: 16268.14 | M53: 2026-06 | N53: High confidence | O53: 3 | P53: 08 Jun 2026 SQ *DY LOCAL Dee Why AU -$9.98 $16,268.14
A54: 46182 | B54: TRANSPORTFORNSW OPAL CHIPPENDALE AUS | C54: Card xx6220 | Value Date: 05/06/2026 | D54: Transport for NSW | E54: Transport | F54: Essential | G54: confirmed | H54: contains:TRANSPORTFORNSW | I54: -60 | J54: 60 | K54: 0 | L54: 16208.14 | M54: 2026-06 | N54: High confidence | O54: 3 | P54: 09 Jun 2026 TRANSPORTFORNSW OPAL CHIPPENDALE AUS -$60.00 $16,208.14 | Card xx6220 | Value Date: 05/06/2026
A55: 46182 | B55: SP TEA LIFE NORTH SAINT M NS AUS | C55: Card xx0018 | Value Date: 07/06/2026 | D55: TEA LIFE NORTH SAINT M | E55: Dining & Coffee | F55: Discretionary | G55: fallback | H55: fallback:tea | I55: -66.8 | J55: 66.8 | K55: 0 | L55: 16141.34 | M55: 2026-06 | N55: High confidence | O55: 4 | P55: 09 Jun 2026 SP TEA LIFE NORTH SAINT M NS AUS -$66.80 $16,141.34 | Card xx0018 | Value Date: 07/06/2026
A56: 46182 | B56: TRANSPORTFORNSW TAP SYDNEY AUS | C56: Card xx0018 | Value Date: 06/06/2026 | D56: Transport for NSW | E56: Transport | F56: Essential | G56: confirmed | H56: contains:TRANSPORTFORNSW | I56: -4.03 | J56: 4.03 | K56: 0 | L56: 16137.31 | M56: 2026-06 | N56: High confidence | O56: 4 | P56: 09 Jun 2026 TRANSPORTFORNSW TAP SYDNEY AUS -$4.03 $16,137.31 | Card xx0018 | Value Date: 06/06/2026
A57: 46182 | B57: LA DISPENSA DEE WHY AUS | C57: Card xx0018 | Value Date: 06/06/2026 | D57: LA DISPENSA DEE WHY | E57: Other | F57: Unknown | G57: unmatched | I57: -11.99 | J57: 11.99 | K57: 0 | L57: 16125.32 | M57: 2026-06 | N57: High confidence | O57: 4 | P57: 09 Jun 2026 LA DISPENSA DEE WHY AUS -$11.99 $16,125.32 | Card xx0018 | Value Date: 06/06/2026
A58: 46182 | B58: AMPOL BROOKVALE 22683F BROOKVALE AUS | C58: Card xx0018 | Value Date: 06/06/2026 | D58: AMPOL BROOKVALE 22683F BROOKVALE | E58: Transport | F58: Essential | G58: fallback | H58: fallback:ampol | I58: -5.5 | J58: 5.5 | K58: 0 | L58: 16119.82 | M58: 2026-06 | N58: High confidence | O58: 4 | P58: 09 Jun 2026 AMPOL BROOKVALE 22683F BROOKVALE AUS -$5.50 $16,119.82 | Card xx0018 | Value Date: 06/06/2026
A59: 46182 | B59: ECKERSLEYS PTY LIMITE BROOKVALE AUS | C59: Card xx0018 | Value Date: 06/06/2026 | D59: ECKERSLEYS PTY LIMITE BROOKVALE | E59: Other | F59: Unknown | G59: unmatched | I59: -19.5 | J59: 19.5 | K59: 0 | L59: 16100.32 | M59: 2026-06 | N59: High confidence | O59: 4 | P59: 09 Jun 2026 ECKERSLEYS PTY LIMITE BROOKVALE AUS -$19.50 $16,100.32 | Card xx0018 | Value Date: 06/06/2026
A60: 46182 | B60: ST VIN DE PAUL SOC NSW BROOKVALE AUS | C60: Card xx0018 | Value Date: 06/06/2026 | D60: ST VIN DE PAUL SOC BROOKVALE | E60: Other | F60: Unknown | G60: unmatched | I60: -3 | J60: 3 | K60: 0 | L60: 16097.32 | M60: 2026-06 | N60: High confidence | O60: 4 | P60: 09 Jun 2026 ST VIN DE PAUL SOC NSW BROOKVALE AUS -$3.00 $16,097.32 | Card xx0018 | Value Date: 06/06/2026
A61: 46182 | B61: WOOLWORTHS 1472 DEE WHY NS AUS | C61: Card xx0018 | Value Date: 06/06/2026 | D61: WOOLWORTHS 1472 DEE WHY | E61: Groceries | F61: Essential | G61: fallback | H61: fallback:woolworths | I61: -49.54 | J61: 49.54 | K61: 0 | L61: 16047.78 | M61: 2026-06 | N61: High confidence | O61: 4 | P61: 09 Jun 2026 WOOLWORTHS 1472 DEE WHY NS AUS -$49.54 $16,047.78 | Card xx0018 | Value Date: 06/06/2026
A62: 46182 | B62: TRANSPORTFORNSW TAP SYDNEY AUS | C62: Card xx0018 | Value Date: 05/06/2026 | D62: Transport for NSW | E62: Transport | F62: Essential | G62: confirmed | H62: contains:TRANSPORTFORNSW | I62: -5.77 | J62: 5.77 | K62: 0 | L62: 16042.01 | M62: 2026-06 | N62: High confidence | O62: 4 | P62: 09 Jun 2026 TRANSPORTFORNSW TAP SYDNEY AUS -$5.77 $16,042.01 | Card xx0018 | Value Date: 05/06/2026
A63: 46182 | B63: BETTYS BURGERS CHADSTONE VI AUS | C63: Card xx0018 | Value Date: 05/06/2026 | D63: Betty's Burgers | E63: Dining & Coffee | F63: Discretionary | G63: confirmed | H63: contains:BETTYS BURGERS | I63: -12.5 | J63: 12.5 | K63: 0 | L63: 16029.51 | M63: 2026-06 | N63: High confidence | O63: 4 | P63: 09 Jun 2026 BETTYS BURGERS CHADSTONE VI AUS -$12.50 $16,029.51 | Card xx0018 | Value Date: 05/06/2026
A64: 46182 | B64: LS MUCHO ALOHA BARS PT Sydney AU AUS | C64: Card xx0018 | Value Date: 05/06/2026 | D64: MUCHO ALOHA BARS PT Sydney | E64: Other | F64: Unknown | G64: unmatched | I64: -50.62 | J64: 50.62 | K64: 0 | L64: 15978.89 | M64: 2026-06 | N64: High confidence | O64: 4 | P64: 09 Jun 2026 LS MUCHO ALOHA BARS PT Sydney AU AUS -$50.62 $15,978.89 | Card xx0018 | Value Date: 05/06/2026
A65: 46182 | B65: SQ *KAHII Sydney AU | D65: Kahii | E65: Dining & Coffee | F65: Discretionary | G65: suggested | H65: contains:KAHII | I65: -7.1 | J65: 7.1 | K65: 0 | L65: 15971.79 | M65: 2026-06 | N65: High confidence | O65: 4 | P65: 09 Jun 2026 SQ *KAHII Sydney AU -$7.10 $15,971.79
A66: 46182 | B66: SQ *T TOTALER Sydney AU | D66: T TOTALER Sydney | E66: Dining & Coffee | F66: Discretionary | G66: fallback | H66: fallback:totaler | I66: -9.65 | J66: 9.65 | K66: 0 | L66: 15962.14 | M66: 2026-06 | N66: High confidence | O66: 4 | P66: 09 Jun 2026 SQ *T TOTALER Sydney AU -$9.65 $15,962.14
A67: 46182 | B67: IMT 1200002130485 Emily Paula Klobuchar | C67: REF K036403075872 | USD 137.56 Rate_0.6878 | Value Date_09/06/2026 | D67: IMT Emily Paula Klobuchar | E67: Transfer Out | F67: Transfer | G67: system | I67: -200 | J67: 200 | K67: 0 | L67: 15762.14 | M67: 2026-06 | N67: High confidence | O67: 4 | P67: 09 Jun 2026 IMT 1200002130485 Emily Paula Klobuchar -$200.00 $15,762.14 | REF K036403075872 | USD 137.56 Rate_0.6878 | Value Date_09/06/2026
A68: 46183 | B68: AMAZON AU MARKETPLACE SYDNEY AUS | C68: Card xx6220 | Value Date: 07/06/2026 | D68: AMAZON MARKETPLACE SYDNEY | E68: Shopping | F68: Discretionary | G68: fallback | H68: fallback:amazon au | I68: -15.89 | J68: 15.89 | K68: 0 | L68: 15746.25 | M68: 2026-06 | N68: High confidence | O68: 4 | P68: 10 Jun 2026 AMAZON AU MARKETPLACE SYDNEY AUS -$15.89 $15,746.25 | Card xx6220 | Value Date: 07/06/2026
A69: 46183 | B69: COLES 0784 DEE WHY NS AUS | C69: Card xx2810 | Value Date: 08/06/2026 | D69: COLES 0784 DEE WHY | E69: Groceries | F69: Essential | G69: fallback | H69: fallback:coles | I69: -80.31 | J69: 80.31 | K69: 0 | L69: 15665.94 | M69: 2026-06 | N69: High confidence | O69: 4 | P69: 10 Jun 2026 COLES 0784 DEE WHY NS AUS -$80.31 $15,665.94 | Card xx2810 | Value Date: 08/06/2026
A70: 46183 | B70: GUZMAN Y GOMEZ 0291910900 AU AUS | C70: Card xx0018 | Value Date: 08/06/2026 | D70: GUZMAN Y GOMEZ | E70: Dining & Coffee | F70: Discretionary | G70: fallback | H70: fallback:guzman | I70: -19.43 | J70: 19.43 | K70: 0 | L70: 15646.51 | M70: 2026-06 | N70: High confidence | O70: 4 | P70: 10 Jun 2026 GUZMAN Y GOMEZ 0291910900 AU AUS -$19.43 $15,646.51 | Card xx0018 | Value Date: 08/06/2026
A71: 46183 | B71: DODO SERVICES PTY LTD MELBOURNE VI AUS | C71: Card xx0018 | Value Date: 08/06/2026 | D71: DODO SERVICES PTY LTD MELBOURNE | E71: Utilities & Phone | F71: Essential | G71: fallback | H71: fallback:dodo services | I71: -71.99 | J71: 71.99 | K71: 0 | L71: 15574.52 | M71: 2026-06 | N71: High confidence | O71: 5 | P71: 10 Jun 2026 DODO SERVICES PTY LTD MELBOURNE VI AUS -$71.99 $15,574.52 | Card xx0018 | Value Date: 08/06/2026
A72: 46183 | B72: SQ *KAHII Sydney AU | D72: Kahii | E72: Dining & Coffee | F72: Discretionary | G72: suggested | H72: contains:KAHII | I72: -7.1 | J72: 7.1 | K72: 0 | L72: 15567.42 | M72: 2026-06 | N72: High confidence | O72: 5 | P72: 10 Jun 2026 SQ *KAHII Sydney AU -$7.10 $15,567.42
A73: 46183 | B73: SQ *PYRMONT KEBAB Pyrmont AU | D73: PYRMONT KEBAB Pyrmont | E73: Dining & Coffee | F73: Discretionary | G73: fallback | H73: fallback:kebab | I73: -15.24 | J73: 15.24 | K73: 0 | L73: 15552.18 | M73: 2026-06 | N73: High confidence | O73: 5 | P73: 10 Jun 2026 SQ *PYRMONT KEBAB Pyrmont AU -$15.24 $15,552.18
A74: 46183 | B74: SMP*Hero Sushi Dee Why Dee Why02 AU | D74: Hero Sushi Dee Why Dee Why02 | E74: Dining & Coffee | F74: Discretionary | G74: fallback | H74: fallback:sushi | I74: -4.85 | J74: 4.85 | K74: 0 | L74: 15547.33 | M74: 2026-06 | N74: High confidence | O74: 5 | P74: 10 Jun 2026 SMP*Hero Sushi Dee Why Dee Why02 AU -$4.85 $15,547.33
A75: 46183 | B75: Direct Debit 507156 MBAUDPayments | C75: AMBITIONS_Ufp2vJgd | D75: Direct Debit 507156 MBAUDPayments | E75: Fitness & Memberships | F75: Discretionary | G75: fallback | H75: fallback:mbaudpayments | I75: -68 | J75: 68 | K75: 0 | L75: 15479.33 | M75: 2026-06 | N75: High confidence | O75: 5 | P75: 10 Jun 2026 Direct Debit 507156 MBAUDPayments -$68.00 $15,479.33 | AMBITIONS_Ufp2vJgd
A76: 46184 | B76: BITE* BBDEE WHY SANCROX NS AUS | C76: Card xx2810 | Value Date: 09/06/2026 | D76: BITE* BBDEE WHY SANCROX | E76: Dining & Coffee | F76: Discretionary | G76: fallback | H76: fallback:bite* | I76: -27.78 | J76: 27.78 | K76: 0 | L76: 15451.55 | M76: 2026-06 | N76: High confidence | O76: 5 | P76: 11 Jun 2026 BITE* BBDEE WHY SANCROX NS AUS -$27.78 $15,451.55 | Card xx2810 | Value Date: 09/06/2026
A77: 46184 | B77: HUNGRYPANDA AU PRAHRAN VI AUS | C77: Card xx0018 | Value Date: 09/06/2026 | D77: HungryPanda | E77: Dining & Coffee | F77: Discretionary | G77: confirmed | H77: contains:HUNGRYPANDA | I77: -16.39 | J77: 16.39 | K77: 0 | L77: 15435.16 | M77: 2026-06 | N77: High confidence | O77: 5 | P77: 11 Jun 2026 HUNGRYPANDA AU PRAHRAN VI AUS -$16.39 $15,435.16 | Card xx0018 | Value Date: 09/06/2026
A78: 46184 | B78: SQ *CHINATOWN COUNTRY Sydney AU | D78: CHINATOWN COUNTRY Sydney | E78: Dining & Coffee | F78: Discretionary | G78: fallback | H78: fallback:chinatown country | I78: -5 | J78: 5 | K78: 0 | L78: 15430.16 | M78: 2026-06 | N78: High confidence | O78: 5 | P78: 11 Jun 2026 SQ *CHINATOWN COUNTRY Sydney AU -$5.00 $15,430.16
A79: 46184 | B79: SQ *BUREAU CAFE Sydney AU | D79: BUREAU CAFE Sydney | E79: Dining & Coffee | F79: Discretionary | G79: fallback | H79: fallback:cafe | I79: -4.5 | J79: 4.5 | K79: 0 | L79: 15425.66 | M79: 2026-06 | N79: High confidence | O79: 5 | P79: 11 Jun 2026 SQ *BUREAU CAFE Sydney AU -$4.50 $15,425.66
A80: 46184 | B80: SQ *LIME ESPRESSO Sydney AU | D80: LIME ESPRESSO Sydney | E80: Dining & Coffee | F80: Discretionary | G80: fallback | H80: fallback:espresso | I80: -14.11 | J80: 14.11 | K80: 0 | L80: 15411.55 | M80: 2026-06 | N80: High confidence | O80: 5 | P80: 11 Jun 2026 SQ *LIME ESPRESSO Sydney AU -$14.11 $15,411.55
A81: 46184 | B81: Direct Debit 518073 Crunch Fitness - | C81: EZYPAYID_99597645 | D81: Direct Debit 518073 Crunch Fitness | E81: Fitness & Memberships | F81: Discretionary | G81: fallback | H81: fallback:crunch fitness | I81: -22.9 | J81: 22.9 | K81: 0 | L81: 15388.65 | M81: 2026-06 | N81: High confidence | O81: 5 | P81: 11 Jun 2026 Direct Debit 518073 Crunch Fitness - -$22.90 $15,388.65 | EZYPAYID_99597645
A82: 46184 | B82: Direct Debit 518073 Crunch Fitness - | C82: EZYPAYID_99598093 | D82: Direct Debit 518073 Crunch Fitness | E82: Fitness & Memberships | F82: Discretionary | G82: fallback | H82: fallback:crunch fitness | I82: -30.9 | J82: 30.9 | K82: 0 | L82: 15357.75 | M82: 2026-06 | N82: High confidence | O82: 5 | P82: 11 Jun 2026 Direct Debit 518073 Crunch Fitness - -$30.90 $15,357.75 | EZYPAYID_99598093
A83: 46185 | B83: COLES 0784 DEE WHY NS AUS | C83: Card xx2810 | Value Date: 10/06/2026 | D83: COLES 0784 DEE WHY | E83: Groceries | F83: Essential | G83: fallback | H83: fallback:coles | I83: -26.68 | J83: 26.68 | K83: 0 | L83: 15331.07 | M83: 2026-06 | N83: High confidence | O83: 5 | P83: 12 Jun 2026 COLES 0784 DEE WHY NS AUS -$26.68 $15,331.07 | Card xx2810 | Value Date: 10/06/2026
A84: 46185 | B84: TRANSPORTFORNSW TAP SYDNEY AUS | C84: Card xx0018 | Value Date: 10/06/2026 | D84: Transport for NSW | E84: Transport | F84: Essential | G84: confirmed | H84: contains:TRANSPORTFORNSW | I84: -4.03 | J84: 4.03 | K84: 0 | L84: 15327.04 | M84: 2026-06 | N84: High confidence | O84: 5 | P84: 12 Jun 2026 TRANSPORTFORNSW TAP SYDNEY AUS -$4.03 $15,327.04 | Card xx0018 | Value Date: 10/06/2026
A85: 46185 | B85: MAPPEN 10 PTY LTD SYDNEY AU | D85: MAPPEN 10 PTY LTD SYDNEY | E85: Dining & Coffee | F85: Discretionary | G85: fallback | H85: fallback:mappen | I85: -32.3 | J85: 32.3 | K85: 0 | L85: 15294.74 | M85: 2026-06 | N85: High confidence | O85: 5 | P85: 12 Jun 2026 MAPPEN 10 PTY LTD SYDNEY AU -$32.30 $15,294.74
A86: 46185 | B86: Molly Tea Regent Plac Sydney AU | D86: Molly Tea Regent Plac Sydney | E86: Dining & Coffee | F86: Discretionary | G86: fallback | H86: fallback:tea | I86: -9.65 | J86: 9.65 | K86: 0 | L86: 15285.09 | M86: 2026-06 | N86: High confidence | O86: 5 | P86: 12 Jun 2026 Molly Tea Regent Plac Sydney AU -$9.65 $15,285.09
A87: 46185 | B87: Fast Transfer From MYO MYO SO to PayID Phone Ramen TY! | D87: Fast Transfer From MYO MYO SO to PayID Phone Ramen TY! | E87: Transfer In | F87: Transfer | G87: system | I87: 15 | J87: 0 | K87: 15 | L87: 15300.09 | M87: 2026-06 | N87: High confidence | O87: 5 | P87: 12 Jun 2026 Fast Transfer From MYO MYO SO $15.00 $15,300.09 | to PayID Phone | Ramen TY!
A88: 46185 | B88: SQ *WINGMILL Dee Why AU | D88: WINGMILL Dee Why | E88: Dining & Coffee | F88: Discretionary | G88: fallback | H88: fallback:wingmill | I88: -46 | J88: 46 | K88: 0 | L88: 15254.09 | M88: 2026-06 | N88: High confidence | O88: 5 | P88: 12 Jun 2026 SQ *WINGMILL Dee Why AU -$46.00 $15,254.09
A89: 46185 | B89: LIQUORLAND 3626 DEE WHY AU | D89: LIQUORLAND 3626 DEE WHY | E89: Dining & Coffee | F89: Discretionary | G89: fallback | H89: fallback:liquor | I89: -22 | J89: 22 | K89: 0 | L89: 15232.09 | M89: 2026-06 | N89: High confidence | O89: 5 | P89: 12 Jun 2026 LIQUORLAND 3626 DEE WHY AU -$22.00 $15,232.09
A90: 46186 | B90: Chargrill Dee Why Dee Why NS AUS | C90: Card xx2810 | Value Date: 11/06/2026 | D90: Chargrill Dee Why Dee Why | E90: Dining & Coffee | F90: Discretionary | G90: fallback | H90: fallback:grill | I90: -22.13 | J90: 22.13 | K90: 0 | L90: 15209.96 | M90: 2026-06 | N90: High confidence | O90: 5 | P90: 13 Jun 2026 Chargrill Dee Why Dee Why NS AUS -$22.13 $15,209.96 | Card xx2810 | Value Date: 11/06/2026
A91: 46186 | B91: BITE* BBDEE WHY SANCROX NS AUS | C91: Card xx2810 | Value Date: 11/06/2026 | D91: BITE* BBDEE WHY SANCROX | E91: Dining & Coffee | F91: Discretionary | G91: fallback | H91: fallback:bite* | I91: -31.85 | J91: 31.85 | K91: 0 | L91: 15178.11 | M91: 2026-06 | N91: High confidence | O91: 5 | P91: 13 Jun 2026 BITE* BBDEE WHY SANCROX NS AUS -$31.85 $15,178.11 | Card xx2810 | Value Date: 11/06/2026
A92: 46186 | B92: AMAZON AU MARKETPLACE SYDNEY AUS | C92: Card xx6220 | Value Date: 10/06/2026 | D92: AMAZON MARKETPLACE SYDNEY | E92: Shopping | F92: Discretionary | G92: fallback | H92: fallback:amazon au | I92: -35.02 | J92: 35.02 | K92: 0 | L92: 15143.09 | M92: 2026-06 | N92: High confidence | O92: 6 | P92: 13 Jun 2026 AMAZON AU MARKETPLACE SYDNEY AUS -$35.02 $15,143.09 | Card xx6220 | Value Date: 10/06/2026
A93: 46186 | B93: TRANSPORTFORNSW TAP SYDNEY AUS | C93: Card xx0018 | Value Date: 11/06/2026 | D93: Transport for NSW | E93: Transport | F93: Essential | G93: confirmed | H93: contains:TRANSPORTFORNSW | I93: -4.03 | J93: 4.03 | K93: 0 | L93: 15139.06 | M93: 2026-06 | N93: High confidence | O93: 6 | P93: 13 Jun 2026 TRANSPORTFORNSW TAP SYDNEY AUS -$4.03 $15,139.06 | Card xx0018 | Value Date: 11/06/2026
A94: 46186 | B94: COLES 0784 DEE WHY AU | D94: COLES 0784 DEE WHY | E94: Groceries | F94: Essential | G94: fallback | H94: fallback:coles | I94: -10 | J94: 10 | K94: 0 | L94: 15129.06 | M94: 2026-06 | N94: High confidence | O94: 6 | P94: 13 Jun 2026 COLES 0784 DEE WHY AU -$10.00 $15,129.06
A95: 46186 | B95: IGA DEE WHY L0347 DEE WHY NSW AU | D95: IGA DEE WHY L0347 DEE WHY | E95: Groceries | F95: Essential | G95: fallback | H95: fallback:iga | I95: -4.49 | J95: 4.49 | K95: 0 | L95: 15124.57 | M95: 2026-06 | N95: High confidence | O95: 6 | P95: 13 Jun 2026 IGA DEE WHY L0347 DEE WHY NSW AU -$4.49 $15,124.57
A96: 46186 | B96: COLES 0784 DEE WHY AU | D96: COLES 0784 DEE WHY | E96: Groceries | F96: Essential | G96: fallback | H96: fallback:coles | I96: -3.5 | J96: 3.5 | K96: 0 | L96: 15121.07 | M96: 2026-06 | N96: High confidence | O96: 6 | P96: 13 Jun 2026 COLES 0784 DEE WHY AU -$3.50 $15,121.07
A97: 46186 | B97: COLES 0784 DEE WHY AU | D97: COLES 0784 DEE WHY | E97: Groceries | F97: Essential | G97: fallback | H97: fallback:coles | I97: -13.8 | J97: 13.8 | K97: 0 | L97: 15107.27 | M97: 2026-06 | N97: High confidence | O97: 6 | P97: 13 Jun 2026 COLES 0784 DEE WHY AU -$13.80 $15,107.27
A98: 46187 | B98: SQ *SACREBLEU ! CANELE dee why AU | D98: SACREBLEU ! CANELE dee why | E98: Dining & Coffee | F98: Discretionary | G98: fallback | H98: fallback:canele | I98: -19.09 | J98: 19.09 | K98: 0 | L98: 15088.18 | M98: 2026-06 | N98: High confidence | O98: 6 | P98: 14 Jun 2026 SQ *SACREBLEU ! CANELE dee why AU -$19.09 $15,088.18
A99: 46187 | B99: SQ *SACREBLEU ! CANELE dee why AU | D99: SACREBLEU ! CANELE dee why | E99: Dining & Coffee | F99: Discretionary | G99: fallback | H99: fallback:canele | I99: -10.16 | J99: 10.16 | K99: 0 | L99: 15078.02 | M99: 2026-06 | N99: High confidence | O99: 6 | P99: 14 Jun 2026 SQ *SACREBLEU ! CANELE dee why AU -$10.16 $15,078.02
A100: 46188 | B100: Direct Debit 545383 Telstra Services | C100: 5scxam67 | D100: Direct Debit 545383 Telstra Services | E100: Utilities & Phone | F100: Essential | G100: fallback | H100: fallback:telstra services | I100: -138 | J100: 138 | K100: 0 | L100: 14940.02 | M100: 2026-06 | N100: High confidence | O100: 6 | P100: 15 Jun 2026 Direct Debit 545383 Telstra Services -$138.00 $14,940.02 | 5scxam67
...

Sheet Monthly Summary
A1: Month | B1: Recurring Income | C1: Refunds / Other Income | D1: Transfer In | E1: Essential Spend | F1: Discretionary Spend | G1: Irregular Spend | H1: Work/Admin Spend | I1: Unknown Spend | J1: Total Spend excl. Transfers | K1: Transfer Out | L1: Net Cash Flow
A2: 2026-06 | B2: =SUMIFS(Transactions!$K$2:$K$788,Transactions!$M$2:$M$788,$A2,Transactions!$E$2:$E$788,"Income - Recurring Direct Credit") -> 11573.71 | C2: =SUMIFS(Transactions!$K$2:$K$788,Transactions!$M$2:$M$788,$A2,Transactions!$E$2:$E$788,"Income - Refund/Reimbursement")+SUMIFS(Transactions!$K$2:$K$788,Transactions!$M$2:$M$788,$A2,Transactions!$E$2:$E$788,"Income - Other Credit") -> 0 | D2: =SUMIFS(Transactions!$K$2:$K$788,Transactions!$M$2:$M$788,$A2,Transactions!$E$2:$E$788,"Transfer In") -> 15 | E2: =SUMIFS(Transactions!$J$2:$J$788,Transactions!$M$2:$M$788,$A2,Transactions!$F$2:$F$788,"Essential") -> 5587.98 | F2: =SUMIFS(Transactions!$J$2:$J$788,Transactions!$M$2:$M$788,$A2,Transactions!$F$2:$F$788,"Discretionary") -> 3082.2 | G2: =SUMIFS(Transactions!$J$2:$J$788,Transactions!$M$2:$M$788,$A2,Transactions!$F$2:$F$788,"Irregular") -> 1895.93 | H2: =SUMIFS(Transactions!$J$2:$J$788,Transactions!$M$2:$M$788,$A2,Transactions!$F$2:$F$788,"Work/Admin") -> 150.45 | I2: =SUMIFS(Transactions!$J$2:$J$788,Transactions!$M$2:$M$788,$A2,Transactions!$F$2:$F$788,"Unknown") -> 570.97 | J2: =SUM(E2:I2) -> 11287.53 | K2: =SUMIFS(Transactions!$J$2:$J$788,Transactions!$M$2:$M$788,$A2,Transactions!$E$2:$E$788,"Transfer Out") -> 1324 | L2: =B2+C2+D2-J2-K2 -> -1022.82
A3: 2026-07 | B3: =SUMIFS(Transactions!$K$2:$K$788,Transactions!$M$2:$M$788,$A3,Transactions!$E$2:$E$788,"Income - Recurring Direct Credit") -> 9455.02 | C3: =SUMIFS(Transactions!$K$2:$K$788,Transactions!$M$2:$M$788,$A3,Transactions!$E$2:$E$788,"Income - Refund/Reimbursement")+SUMIFS(Transactions!$K$2:$K$788,Transactions!$M$2:$M$788,$A3,Transactions!$E$2:$E$788,"Income - Other Credit") -> 296.01 | D3: =SUMIFS(Transactions!$K$2:$K$788,Transactions!$M$2:$M$788,$A3,Transactions!$E$2:$E$788,"Transfer In") -> 20001.4 | E3: =SUMIFS(Transactions!$J$2:$J$788,Transactions!$M$2:$M$788,$A3,Transactions!$F$2:$F$788,"Essential") -> 7483.61 | F3: =SUMIFS(Transactions!$J$2:$J$788,Transactions!$M$2:$M$788,$A3,Transactions!$F$2:$F$788,"Discretionary") -> 2951.8 | G3: =SUMIFS(Transactions!$J$2:$J$788,Transactions!$M$2:$M$788,$A3,Transactions!$F$2:$F$788,"Irregular") -> 1054.9 | H3: =SUMIFS(Transactions!$J$2:$J$788,Transactions!$M$2:$M$788,$A3,Transactions!$F$2:$F$788,"Work/Admin") -> 424.88 | I3: =SUMIFS(Transactions!$J$2:$J$788,Transactions!$M$2:$M$788,$A3,Transactions!$F$2:$F$788,"Unknown") -> 1117.74 | J3: =SUM(E3:I3) -> 13032.93 | K3: =SUMIFS(Transactions!$J$2:$J$788,Transactions!$M$2:$M$788,$A3,Transactions!$E$2:$E$788,"Transfer Out") -> 5988.89 | L3: =B3+C3+D3-J3-K3 -> 10730.61
A4: 2026-08 | B4: =SUMIFS(Transactions!$K$2:$K$788,Transactions!$M$2:$M$788,$A4,Transactions!$E$2:$E$788,"Income - Recurring Direct Credit") -> 10281.64 | C4: =SUMIFS(Transactions!$K$2:$K$788,Transactions!$M$2:$M$788,$A4,Transactions!$E$2:$E$788,"Income - Refund/Reimbursement")+SUMIFS(Transactions!$K$2:$K$788,Transactions!$M$2:$M$788,$A4,Transactions!$E$2:$E$788,"Income - Other Credit") -> 729.8 | D4: =SUMIFS(Transactions!$K$2:$K$788,Transactions!$M$2:$M$788,$A4,Transactions!$E$2:$E$788,"Transfer In") -> 0 | E4: =SUMIFS(Transactions!$J$2:$J$788,Transactions!$M$2:$M$788,$A4,Transactions!$F$2:$F$788,"Essential") -> 6319.2 | F4: =SUMIFS(Transactions!$J$2:$J$788,Transactions!$M$2:$M$788,$A4,Transactions!$F$2:$F$788,"Discretionary") -> 2795.99 | G4: =SUMIFS(Transactions!$J$2:$J$788,Transactions!$M$2:$M$788,$A4,Transactions!$F$2:$F$788,"Irregular") -> 526 | H4: =SUMIFS(Transactions!$J$2:$J$788,Transactions!$M$2:$M$788,$A4,Transactions!$F$2:$F$788,"Work/Admin") -> 869.32 | I4: =SUMIFS(Transactions!$J$2:$J$788,Transactions!$M$2:$M$788,$A4,Transactions!$F$2:$F$788,"Unknown") -> 1411.1 | J4: =SUM(E4:I4) -> 11921.61 | K4: =SUMIFS(Transactions!$J$2:$J$788,Transactions!$M$2:$M$788,$A4,Transactions!$E$2:$E$788,"Transfer Out") -> 6 | L4: =B4+C4+D4-J4-K4 -> -916.17
A5: 2026-09 | B5: =SUMIFS(Transactions!$K$2:$K$788,Transactions!$M$2:$M$788,$A5,Transactions!$E$2:$E$788,"Income - Recurring Direct Credit") -> 0 | C5: =SUMIFS(Transactions!$K$2:$K$788,Transactions!$M$2:$M$788,$A5,Transactions!$E$2:$E$788,"Income - Refund/Reimbursement")+SUMIFS(Transactions!$K$2:$K$788,Transactions!$M$2:$M$788,$A5,Transactions!$E$2:$E$788,"Income - Other Credit") -> 67.6 | D5: =SUMIFS(Transactions!$K$2:$K$788,Transactions!$M$2:$M$788,$A5,Transactions!$E$2:$E$788,"Transfer In") -> 0 | E5: =SUMIFS(Transactions!$J$2:$J$788,Transactions!$M$2:$M$788,$A5,Transactions!$F$2:$F$788,"Essential") -> 1400.04 | F5: =SUMIFS(Transactions!$J$2:$J$788,Transactions!$M$2:$M$788,$A5,Transactions!$F$2:$F$788,"Discretionary") -> 698.81 | G5: =SUMIFS(Transactions!$J$2:$J$788,Transactions!$M$2:$M$788,$A5,Transactions!$F$2:$F$788,"Irregular") -> 762 | H5: =SUMIFS(Transactions!$J$2:$J$788,Transactions!$M$2:$M$788,$A5,Transactions!$F$2:$F$788,"Work/Admin") -> 490 | I5: =SUMIFS(Transactions!$J$2:$J$788,Transactions!$M$2:$M$788,$A5,Transactions!$F$2:$F$788,"Unknown") -> 517.94 | J5: =SUM(E5:I5) -> 3868.79 | K5: =SUMIFS(Transactions!$J$2:$J$788,Transactions!$M$2:$M$788,$A5,Transactions!$E$2:$E$788,"Transfer Out") -> 7 | L5: =B5+C5+D5-J5-K5 -> -3808.19

Sheet Budget
A1: Suggested Monthly Budget
A2: Recurring-income baseline | B2: =MEDIAN('Monthly Summary'!B2,'Monthly Summary'!B3,'Monthly Summary'!B4) -> 10281.64
A4: Category | B4: 2026-06 | C4: 2026-07 | D4: 2026-08 | E4: Average | F4: Suggested Cap | G4: Cap vs Avg | H4: Comment
A5: Housing - Rent | B5: =SUMIFS(Transactions!$J$2:$J$788,Transactions!$M$2:$M$788,"2026-06",Transactions!$E$2:$E$788,$A5) -> 3440 | C5: =SUMIFS(Transactions!$J$2:$J$788,Transactions!$M$2:$M$788,"2026-07",Transactions!$E$2:$E$788,$A5) -> 5160 | D5: =SUMIFS(Transactions!$J$2:$J$788,Transactions!$M$2:$M$788,"2026-08",Transactions!$E$2:$E$788,$A5) -> 3440 | E5: =AVERAGE(B5:D5) -> 4013.3333 | F5: 3683 | G5: =F5-E5 -> -330.33333 | H5: Fortnightly $1,700 normalized to 26 payments / 12 months.
A6: Groceries | B6: =SUMIFS(Transactions!$J$2:$J$788,Transactions!$M$2:$M$788,"2026-06",Transactions!$E$2:$E$788,$A6) -> 842.75 | C6: =SUMIFS(Transactions!$J$2:$J$788,Transactions!$M$2:$M$788,"2026-07",Transactions!$E$2:$E$788,$A6) -> 638.68 | D6: =SUMIFS(Transactions!$J$2:$J$788,Transactions!$M$2:$M$788,"2026-08",Transactions!$E$2:$E$788,$A6) -> 867.84 | E6: =AVERAGE(B6:D6) -> 783.09 | F6: 550 | G6: =F6-E6 -> -233.09 | H6: Baseline allowance for supermarket / grocery spending.
A7: Dining & Coffee | B7: =SUMIFS(Transactions!$J$2:$J$788,Transactions!$M$2:$M$788,"2026-06",Transactions!$E$2:$E$788,$A7) -> 1680.52 | C7: =SUMIFS(Transactions!$J$2:$J$788,Transactions!$M$2:$M$788,"2026-07",Transactions!$E$2:$E$788,$A7) -> 1621.37 | D7: =SUMIFS(Transactions!$J$2:$J$788,Transactions!$M$2:$M$788,"2026-08",Transactions!$E$2:$E$788,$A7) -> 1197.92 | E7: =AVERAGE(B7:D7) -> 1499.9367 | F7: 650 | G7: =F7-E7 -> -849.93667 | H7: A controllable category; target is below the observed run-rate.
A8: Utilities & Phone | B8: =SUMIFS(Transactions!$J$2:$J$788,Transactions!$M$2:$M$788,"2026-06",Transactions!$E$2:$E$788,$A8) -> 607.42 | C8: =SUMIFS(Transactions!$J$2:$J$788,Transactions!$M$2:$M$788,"2026-07",Transactions!$E$2:$E$788,$A8) -> 228.94 | D8: =SUMIFS(Transactions!$J$2:$J$788,Transactions!$M$2:$M$788,"2026-08",Transactions!$E$2:$E$788,$A8) -> 452.48 | E8: =AVERAGE(B8:D8) -> 429.61333 | F8: 350 | G8: =F8-E8 -> -79.613333 | H8: Smooths irregular billing months.
A9: Transport | B9: =SUMIFS(Transactions!$J$2:$J$788,Transactions!$M$2:$M$788,"2026-06",Transactions!$E$2:$E$788,$A9) -> 507.83 | C9: =SUMIFS(Transactions!$J$2:$J$788,Transactions!$M$2:$M$788,"2026-07",Transactions!$E$2:$E$788,$A9) -> 984.84 | D9: =SUMIFS(Transactions!$J$2:$J$788,Transactions!$M$2:$M$788,"2026-08",Transactions!$E$2:$E$788,$A9) -> 454.87 | E9: =AVERAGE(B9:D9) -> 649.18 | F9: 450 | G9: =F9-E9 -> -199.18 | H9: Allows for Opal/Uber/fuel/taxis.
A10: Fitness & Memberships | B10: =SUMIFS(Transactions!$J$2:$J$788,Transactions!$M$2:$M$788,"2026-06",Transactions!$E$2:$E$788,$A10) -> 379.6 | C10: =SUMIFS(Transactions!$J$2:$J$788,Transactions!$M$2:$M$788,"2026-07",Transactions!$E$2:$E$788,$A10) -> 492.5 | D10: =SUMIFS(Transactions!$J$2:$J$788,Transactions!$M$2:$M$788,"2026-08",Transactions!$E$2:$E$788,$A10) -> 379.6 | E10: =AVERAGE(B10:D10) -> 417.23333 | F10: 354 | G10: =F10-E10 -> -63.233333 | H10: Approximately current recurring run-rate.
A11: Health & Pharmacy | B11: =SUMIFS(Transactions!$J$2:$J$788,Transactions!$M$2:$M$788,"2026-06",Transactions!$E$2:$E$788,$A11) -> 183.24 | C11: =SUMIFS(Transactions!$J$2:$J$788,Transactions!$M$2:$M$788,"2026-07",Transactions!$E$2:$E$788,$A11) -> 468.07 | D11: =SUMIFS(Transactions!$J$2:$J$788,Transactions!$M$2:$M$788,"2026-08",Transactions!$E$2:$E$788,$A11) -> 1126.65 | E11: =AVERAGE(B11:D11) -> 592.65333 | F11: 400 | G11: =F11-E11 -> -192.65333 | H11: Buffer for pharmacy/medical variability.
A12: Shopping | B12: =SUMIFS(Transactions!$J$2:$J$788,Transactions!$M$2:$M$788,"2026-06",Transactions!$E$2:$E$788,$A12) -> 830.53 | C12: =SUMIFS(Transactions!$J$2:$J$788,Transactions!$M$2:$M$788,"2026-07",Transactions!$E$2:$E$788,$A12) -> 672.41 | D12: =SUMIFS(Transactions!$J$2:$J$788,Transactions!$M$2:$M$788,"2026-08",Transactions!$E$2:$E$788,$A12) -> 1088.37 | E12: =AVERAGE(B12:D12) -> 863.77 | F12: 600 | G12: =F12-E12 -> -263.77 | H12: Main discretionary reduction target.
A13: Beauty & Personal Care | B13: =SUMIFS(Transactions!$J$2:$J$788,Transactions!$M$2:$M$788,"2026-06",Transactions!$E$2:$E$788,$A13) -> 68.57 | C13: =SUMIFS(Transactions!$J$2:$J$788,Transactions!$M$2:$M$788,"2026-07",Transactions!$E$2:$E$788,$A13) -> 663.51 | D13: =SUMIFS(Transactions!$J$2:$J$788,Transactions!$M$2:$M$788,"2026-08",Transactions!$E$2:$E$788,$A13) -> 120.11 | E13: =AVERAGE(B13:D13) -> 284.06333 | F13: 150 | G13: =F13-E13 -> -134.06333 | H13: Use as a monthly cap / sinking fund.
A14: Home & Household | B14: =SUMIFS(Transactions!$J$2:$J$788,Transactions!$M$2:$M$788,"2026-06",Transactions!$E$2:$E$788,$A14) -> 0 | C14: =SUMIFS(Transactions!$J$2:$J$788,Transactions!$M$2:$M$788,"2026-07",Transactions!$E$2:$E$788,$A14) -> 0 | D14: =SUMIFS(Transactions!$J$2:$J$788,Transactions!$M$2:$M$788,"2026-08",Transactions!$E$2:$E$788,$A14) -> 66.23 | E14: =AVERAGE(B14:D14) -> 22.076667 | F14: 250 | G14: =F14-E14 -> 227.92333 | H14: Sinking fund for irregular household purchases.
A15: Entertainment & Experiences | B15: =SUMIFS(Transactions!$J$2:$J$788,Transactions!$M$2:$M$788,"2026-06",Transactions!$E$2:$E$788,$A15) -> 34.85 | C15: =SUMIFS(Transactions!$J$2:$J$788,Transactions!$M$2:$M$788,"2026-07",Transactions!$E$2:$E$788,$A15) -> 0 | D15: =SUMIFS(Transactions!$J$2:$J$788,Transactions!$M$2:$M$788,"2026-08",Transactions!$E$2:$E$788,$A15) -> 8 | E15: =AVERAGE(B15:D15) -> 14.283333 | F15: 100 | G15: =F15-E15 -> 85.716667 | H15: Monthly leisure allowance.
A16: Subscriptions & Donations | B16: =SUMIFS(Transactions!$J$2:$J$788,Transactions!$M$2:$M$788,"2026-06",Transactions!$E$2:$E$788,$A16) -> 122.98 | C16: =SUMIFS(Transactions!$J$2:$J$788,Transactions!$M$2:$M$788,"2026-07",Transactions!$E$2:$E$788,$A16) -> 9.99 | D16: =SUMIFS(Transactions!$J$2:$J$788,Transactions!$M$2:$M$788,"2026-08",Transactions!$E$2:$E$788,$A16) -> 9.99 | E16: =AVERAGE(B16:D16) -> 47.653333 | F16: 15 | G16: =F16-E16 -> -32.653333 | H16: Recurring subscriptions/donations.
... A21: Other | B21: =SUMIFS(Transactions!$J$2:$J$788,Transactions!$M$2:$M$788,"2026-06",Transactions!$E$2:$E$788,$A21) -> 570.97 | C21: =SUMIFS(Transactions!$J$2:$J$788,Transactions!$M$2:$M$788,"2026-07",Transactions!$E$2:$E$788,$A21) -> 1117.74 | D21: =SUMIFS(Transactions!$J$2:$J$788,Transactions!$M$2:$M$788,"2026-08",Transactions!$E$2:$E$788,$A21) -> 1411.1 | E21: =AVERAGE(B21:D21) -> 1033.27 | F21: 250 | G21: =F21-E21 -> -783.27 | H21: Buffer for merchants not yet confidently categorized.
A22: TOTAL MONTHLY SPEND | B22: =SUM(B5:B21) -> 11137.08 | C22: =SUM(C5:C21) -> 12608.05 | D22: =SUM(D5:D21) -> 11052.29 | E22: =SUM(E5:E21) -> 11599.14 | F22: =SUM(F5:F21) -> 8272 | G22: =SUM(G5:G21) -> -3327.14
A25: Budget outcome
A26: Income baseline | B26: =$B$2 -> 10281.64
A27: Suggested monthly spend | B27: =F22 -> 8272
A28: Implied monthly savings | B28: =B26-B27 -> 2009.64
A29: Savings rate | B29: =IFERROR(B28/B26,0) -> 0.19545909

Sheet Merchant Review
A1: Merchant | B1: Transactions | C1: Total Spend | D1: Median | E1: Average | F1: First Seen | G1: Last Seen | H1: Current Category | I1: Budget Character | J1: Rule Status | K1: Rule Match | L1: Examples | M1: Why review
A2: Kwik Kopy | B2: 1 | C2: 826.62 | D2: 826.62 | E2: 826.62 | F2: 46254 | G2: 46254 | H2: Education & Professional | I2: Work/Admin | J2: suggested | K2: contains:KWIK KOPY | L2: Kwik Kopy Market Stree Sydney NS AUS | M2: Suggested rule — confirm or edit
A3: Think Again Laser | B3: 1 | C3: 507.98 | D3: 507.98 | E3: 507.98 | F3: 46214 | G3: 46214 | H3: Beauty & Personal Care | I3: Irregular | J3: suggested | K3: contains:THINK AGAIN LASER | L3: SMP*Think Again Laser89 Dee Why02 AU | M3: Suggested rule — confirm or edit
A4: SLC WARRINGAH MALL P BROOKVALE | B4: 1 | C4: 499 | D4: 499 | E4: 499 | F4: 46253 | G4: 46253 | H4: Other | I4: Unknown | J4: unmatched | L4: SLC WARRINGAH MALL P BROOKVALE NS AUS | M4: No confirmed merchant rule; Budget character unknown
A5: Worldwide Interpreters | B5: 1 | C5: 391.93 | D5: 391.93 | E5: 391.93 | F5: 46217 | G5: 46217 | H5: Education & Professional | I5: Work/Admin | J5: suggested | K5: contains:WORLDWIDE INTERPRETERS | L5: WORLDWIDE INTERPRETERS | M5: Suggested rule — confirm or edit
A6: BAR COPAINS Surry Hills | B6: 1 | C6: 195.07 | D6: 195.07 | E6: 195.07 | F6: 46266 | G6: 46266 | H6: Other | I6: Unknown | J6: unmatched | L6: SQ *BAR COPAINS Surry Hills NS AUS | M6: No confirmed merchant rule; Budget character unknown
A7: GLOBAL-E* PEPPER MELBOURNE | B7: 1 | C7: 170 | D7: 170 | E7: 170 | F7: 46239 | G7: 46239 | H7: Other | I7: Unknown | J7: unmatched | L7: GLOBAL-E* PEPPER MELBOURNE VI AUS | M7: No confirmed merchant rule; Budget character unknown
A8: Costco | B8: 4 | C8: 161.65 | D8: 9.475 | E8: 40.4125 | F8: 46231 | G8: 46241 | H8: Groceries | I8: Essential | J8: suggested | K8: contains:COSTCO AUBURN, contains:COSTCO WHOLESALE | L8: COSTCO WHOLESALE PTY LIDCOMBE AUS | COSTCO AUBURN LIDCOMBE NS AUS | M8: Suggested rule — confirm or edit
A9: ALL THINGS GOLDEN HAWTHORN | B9: 1 | C9: 133.2 | D9: 133.2 | E9: 133.2 | F9: 46238 | G9: 46238 | H9: Other | I9: Unknown | J9: unmatched | L9: SP ALL THINGS GOLDEN HAWTHORN VI AUS | M9: No confirmed merchant rule; Budget character unknown
A10: Cash Traders Northsid Dee Why | B10: 1 | C10: 130.29 | D10: 130.29 | E10: 130.29 | F10: 46233 | G10: 46233 | H10: Other | I10: Unknown | J10: unmatched | L10: Cash Traders Northsid Dee Why NS AUS | M10: No confirmed merchant rule; Budget character unknown
A11: Kahii | B11: 15 | C11: 112.09 | D11: 7.1 | E11: 7.4726667 | F11: 46174 | G11: 46273 | H11: Dining & Coffee | I11: Discretionary | J11: suggested | K11: contains:KAHII | L11: SQ *KAHII Sydney AU | SQ *KAHII Sydney NS AUS | M11: Suggested rule — confirm or edit
A12: AURIENTO PTY LTD LANE COVE | B12: 2 | C12: 95.8 | D12: 47.9 | E12: 47.9 | F12: 46255 | G12: 46267 | H12: Other | I12: Unknown | J12: unmatched | L12: AURIENTO PTY LTD LANE COVE NS AUS | M12: No confirmed merchant rule; Budget character unknown
A13: IRISH MURPHYS - HOBART BATTERY POINT | B13: 1 | C13: 91.36 | D13: 91.36 | E13: 91.36 | F13: 46217 | G13: 46217 | H13: Other | I13: Unknown | J13: unmatched | L13: IRISH MURPHYS - HOBART BATTERY POINT TA AUS | M13: No confirmed merchant rule; Budget character unknown
A14: WWW.YESDRIVE.COM | B14: 1 | C14: 86.89 | D14: 86.89 | E14: 86.89 | F14: 46265 | G14: 46265 | H14: Other | I14: Unknown | J14: unmatched | L14: WWW.YESDRIVE.COM.AU | M14: No confirmed merchant rule; Budget character unknown
A15: Cuts Avenue | B15: 1 | C15: 84.33 | D15: 84.33 | E15: 84.33 | F15: 46229 | G15: 46229 | H15: Beauty & Personal Care | I15: Discretionary | J15: suggested | K15: contains:CUTS AVENUE | L15: SQ *CUTS AVENUE WARRIN Brookvale AU | M15: Suggested rule — confirm or edit
A16: EJ FAMILY TRUST SYDNEY | B16: 6 | C16: 77.85 | D16: 12.13 | E16: 12.975 | F16: 46189 | G16: 46273 | H16: Other | I16: Unknown | J16: unmatched | L16: EJ FAMILY TRUST SYDNEY NS AUS | M16: No confirmed merchant rule; Budget character unknown
A17: ENTERMISSION SYDNE Sydney | B17: 3 | C17: 70.77 | D17: 30.33 | E17: 23.59 | F17: 46227 | G17: 46227 | H17: Other | I17: Unknown | J17: unmatched | L17: SQ *ENTERMISSION SYDNE Sydney AU | M17: No confirmed merchant rule; Budget character unknown
A18: Henry Gs Manly | B18: 1 | C18: 69.55 | D18: 69.55 | E18: 69.55 | F18: 46273 | G18: 46273 | H18: Other | I18: Unknown | J18: unmatched | L18: Henry Gs Manly AU AUS | M18: No confirmed merchant rule; Budget character unknown
A19: Marys Dee Why Dee Why | B19: 1 | C19: 69.1 | D19: 69.1 | E19: 69.1 | F19: 46210 | G19: 46210 | H19: Other | I19: Unknown | J19: unmatched | L19: LSP*Marys Dee Why Dee Why AU AUS | M19: No confirmed merchant rule; Budget character unknown
A20: ODDCULTURE.GROUP ENMORE | B20: 2 | C20: 66.45 | D20: 33.225 | E20: 33.225 | F20: 46227 | G20: 46227 | H20: Other | I20: Unknown | J20: unmatched | L20: ODDCULTURE.GROUP ENMORE NS AUS | M20: No confirmed merchant rule; Budget character unknown
A21: Barrel Below | B21: 14 | C21: 62.16 | D21: 4.05 | E21: 4.44 | F21: 46245 | G21: 46266 | H21: Dining & Coffee | I21: Discretionary | J21: suggested | K21: contains:BARREL BELOW | L21: SQ *BARREL BELOW Sydney NS AUS | M21: Suggested rule — confirm or edit
A22: Flying Hat | B22: 9 | C22: 59.18 | D22: 6.07 | E22: 6.5755556 | F22: 46177 | G22: 46259 | H22: Dining & Coffee | I22: Discretionary | J22: suggested | K22: contains:FLYING HAT | L22: FLYING HAT SYDNEY AUS | M22: Suggested rule — confirm or edit
A23: DY LOCAL Dee Why | B23: 5 | C23: 53.33 | D23: 10.2 | E23: 10.666 | F23: 46181 | G23: 46266 | H23: Other | I23: Unknown | J23: unmatched | L23: SQ *DY LOCAL Dee Why AU | SQ *DY LOCAL Dee Why NS AUS | M23: No confirmed merchant rule; Budget character unknown
A24: TESSUTO Sydney | B24: 5 | C24: 51.33 | D24: 8.13 | E24: 10.266 | F24: 46227 | G24: 46232 | H24: Other | I24: Unknown | J24: unmatched | L24: TESSUTO Sydney NS AUS | M24: No confirmed merchant rule; Budget character unknown
A25: Austrian Beer Bar a Narrabeen | B25: 1 | C25: 50.88 | D25: 50.88 | E25: 50.88 | F25: 46259 | G25: 46259 | H25: Other | I25: Unknown | J25: unmatched | L25: LS Austrian Beer Bar a Narrabeen AU AUS | M25: No confirmed merchant rule; Budget character unknown
A26: MUCHO ALOHA BARS PT Sydney | B26: 1 | C26: 50.62 | D26: 50.62 | E26: 50.62 | F26: 46182 | G26: 46182 | H26: Other | I26: Unknown | J26: unmatched | L26: LS MUCHO ALOHA BARS PT Sydney AU AUS | M26: No confirmed merchant rule; Budget character unknown
A27: U GO MT COLAH MOUNT COLAH | B27: 1 | C27: 50 | D27: 50 | E27: 50 | F27: 46249 | G27: 46249 | H27: Other | I27: Unknown | J27: unmatched | L27: U GO MT COLAH MOUNT COLAH AU | M27: No confirmed merchant rule; Budget character unknown
A28: SMT SSR PTY LTD BROOKVALE | B28: 1 | C28: 45.45 | D28: 45.45 | E28: 45.45 | F28: 46197 | G28: 46197 | H28: Other | I28: Unknown | J28: unmatched | L28: SMT SSR PTY LTD BROOKVALE AUS | M28: No confirmed merchant rule; Budget character unknown
A29: FARSHAD & REZA PL DEE WHY NSWAU | B29: 1 | C29: 45 | D29: 45 | E29: 45 | F29: 46224 | G29: 46224 | H29: Other | I29: Unknown | J29: unmatched | L29: FARSHAD & REZA PL DEE WHY NSWAU | M29: No confirmed merchant rule; Budget character unknown
A30: BRUNY ISLAND HONEY Great Bay | B30: 1 | C30: 43.5 | D30: 43.5 | E30: 43.5 | F30: 46211 | G30: 46211 | H30: Other | I30: Unknown | J30: unmatched | L30: SQ *BRUNY ISLAND HONEY Great Bay AU | M30: No confirmed merchant rule; Budget character unknown
A31: GS1 US | B31: 1 | C31: 42.7 | D31: 42.7 | E31: 42.7 | F31: 46245 | G31: 46245 | H31: Education & Professional | I31: Work/Admin | J31: suggested | K31: contains:GS1 US | L31: GS1 US, INC. 6096204612 NJ USA | M31: Suggested rule — confirm or edit
A32: HANK'S SPECIALTY C Ettalong Beac | B32: 2 | C32: 42.5 | D32: 21.25 | E32: 21.25 | F32: 46245 | G32: 46245 | H32: Other | I32: Unknown | J32: unmatched | L32: SQ *HANK'S SPECIALTY C Ettalong Beac NS AUS | M32: No confirmed merchant rule; Budget character unknown
A33: The Richmond Chocol Richmond | B33: 1 | C33: 41.08 | D33: 41.08 | E33: 41.08 | F33: 46212 | G33: 46212 | H33: Other | I33: Unknown | J33: unmatched | L33: ZLR*The Richmond Chocol Richmond AU | M33: No confirmed merchant rule; Budget character unknown
A34: LA DISPENSA DEE WHY | B34: 3 | C34: 37.58 | D34: 11.99 | E34: 12.526667 | F34: 46182 | G34: 46224 | H34: Other | I34: Unknown | J34: unmatched | L34: LA DISPENSA DEE WHY AUS | M34: No confirmed merchant rule; Budget character unknown
A35: D M ENTERTAINMENT Manly | B35: 1 | C35: 36.49 | D35: 36.49 | E35: 36.49 | F35: 46215 | G35: 46215 | H35: Other | I35: Unknown | J35: unmatched | L35: SQ *D M ENTERTAINMENT Manly AU | M35: No confirmed merchant rule; Budget character unknown
A36: ALH VENUES 8733 CROWS NEST | B36: 1 | C36: 36.2 | D36: 36.2 | E36: 36.2 | F36: 46196 | G36: 46196 | H36: Other | I36: Unknown | J36: unmatched | L36: ALH VENUES 8733 CROWS NEST NS AUS | M36: No confirmed merchant rule; Budget character unknown
A37: DARYA PERSIAN S'MARKET HORNSBY | B37: 2 | C37: 35.5 | D37: 17.75 | E37: 17.75 | F37: 46249 | G37: 46249 | H37: Other | I37: Unknown | J37: unmatched | L37: DARYA PERSIAN S'MARKET HORNSBY NSW AU | M37: No confirmed merchant rule; Budget character unknown
A38: Claude | B38: 1 | C38: 33.99 | D38: 33.99 | E38: 33.99 | F38: 46198 | G38: 46198 | H38: Subscriptions & Donations | I38: Discretionary | J38: suggested | K38: contains:GOOGLE CLAUDE BY ANTH | L38: Google Claude by Anth Barangaroo AU AUS | M38: Suggested rule — confirm or edit
A39: GUSTO ON THE BEACH Dee Why | B39: 1 | C39: 33.53 | D39: 33.53 | E39: 33.53 | F39: 46180 | G39: 46180 | H39: Other | I39: Unknown | J39: unmatched | L39: SQ *GUSTO ON THE BEACH Dee Why AU | M39: No confirmed merchant rule; Budget character unknown
A40: Cupcakes on Pitt Sydney | B40: 2 | C40: 33.47 | D40: 16.735 | E40: 16.735 | F40: 46223 | G40: 46225 | H40: Other | I40: Unknown | J40: unmatched | L40: ZLR*Cupcakes on Pitt Sydney AU | M40: No confirmed merchant rule; Budget character unknown
A41: OzBarcodes | B41: 1 | C41: 32.95 | D41: 32.95 | E41: 32.95 | F41: 46219 | G41: 46219 | H41: Education & Professional | I41: Work/Admin | J41: suggested | K41: contains:OZBARCODES | L41: OZBARCODES.COM.AU | M41: Suggested rule — confirm or edit
A42: Irish Murphy's Hobart Hobart | B42: 1 | C42: 31.97 | D42: 31.97 | E42: 31.97 | F42: 46217 | G42: 46217 | H42: Other | I42: Unknown | J42: unmatched | L42: Irish Murphy's Hobart Hobart TA AUS | M42: No confirmed merchant rule; Budget character unknown
A43: COAL RIVER FARM*MO Seven Mile Be | B43: 1 | C43: 30.53 | D43: 30.53 | E43: 30.53 | F43: 46217 | G43: 46217 | H43: Other | I43: Unknown | J43: unmatched | L43: SQ *COAL RIVER FARM*MO Seven Mile Be TA AUS | M43: No confirmed merchant rule; Budget character unknown
A44: The Vicars Daughters Collaroy | B44: 2 | C44: 30.49 | D44: 15.245 | E44: 15.245 | F44: 46175 | G44: 46273 | H44: Other | I44: Unknown | J44: unmatched | L44: The Vicars Daughters Collaroy AU AUS | M44: No confirmed merchant rule; Budget character unknown
A45: WARRINGAH North Rocks | B45: 1 | C45: 29.99 | D45: 29.99 | E45: 29.99 | F45: 46229 | G45: 46229 | H45: Other | I45: Unknown | J45: unmatched | L45: LS WARRINGAH North Rocks AU | M45: No confirmed merchant rule; Budget character unknown
A46: SYDNEY SHOWGROUND Sydney Olympi | B46: 2 | C46: 28 | D46: 14 | E46: 14 | F46: 46266 | G46: 46266 | H46: Other | I46: Unknown | J46: unmatched | L46: SQ *SYDNEY SHOWGROUND Sydney Olympi NS AUS | M46: No confirmed merchant rule; Budget character unknown
A47: BEAR WITH ME South Hobart | B47: 1 | C47: 27.56 | D47: 27.56 | E47: 27.56 | F47: 46213 | G47: 46213 | H47: Other | I47: Unknown | J47: unmatched | L47: SQ *BEAR WITH ME South Hobart AU | M47: No confirmed merchant rule; Budget character unknown
A48: FOUR BROTHERS ESPR Warringah Mal | B48: 2 | C48: 27.53 | D48: 13.765 | E48: 13.765 | F48: 46245 | G48: 46266 | H48: Other | I48: Unknown | J48: unmatched | L48: SQ *FOUR BROTHERS ESPR Warringah Mal NS AUS | M48: No confirmed merchant rule; Budget character unknown
A49: CINCIN BEVERAGES Artarmon | B49: 1 | C49: 27 | D49: 27 | E49: 27 | F49: 46193 | G49: 46193 | H49: Other | I49: Unknown | J49: unmatched | L49: SQ *CINCIN BEVERAGES Artarmon AU | M49: No confirmed merchant rule; Budget character unknown
A50: NICHI GETSU DO Sydney | B50: 1 | C50: 26 | D50: 26 | E50: 26 | F50: 46220 | G50: 46220 | H50: Other | I50: Unknown | J50: unmatched | L50: SQ *NICHI GETSU DO Sydney AU | M50: No confirmed merchant rule; Budget character unknown
A51: BRUNY ISLAND GATEW Kettering | B51: 1 | C51: 24.89 | D51: 24.89 | E51: 24.89 | F51: 46211 | G51: 46211 | H51: Other | I51: Unknown | J51: unmatched | L51: SQ *BRUNY ISLAND GATEW Kettering AU | M51: No confirmed merchant rule; Budget character unknown
A52: BENZIN CITY GARAGE Sydney | B52: 1 | C52: 24 | D52: 24 | E52: 24 | F52: 46216 | G52: 46216 | H52: Other | I52: Unknown | J52: unmatched | L52: SQ *BENZIN CITY GARAGE Sydney AU | M52: No confirmed merchant rule; Budget character unknown
A53: WB PROJECT AUSTRAL Artarmon | B53: 1 | C53: 23 | D53: 23 | E53: 23 | F53: 46196 | G53: 46196 | H53: Other | I53: Unknown | J53: unmatched | L53: SQ *WB PROJECT AUSTRAL Artarmon NS AUS | M53: No confirmed merchant rule; Budget character unknown
... A132: Mixue George Street Sydney | B132: 1 | C132: 2.5 | D132: 2.5 | E132: 2.5 | F132: 46231 | G132: 46231 | H132: Other | I132: Unknown | J132: unmatched | L132: Mixue George Street Sydney NS AUS | M132: No confirmed merchant rule; Budget character unknown
A133: Dee Why Library | B133: 2 | C133: 2.1 | D133: 1.05 | E133: 1.05 | F133: 46197 | G133: 46224 | H133: Government & Admin | I133: Irregular | J133: suggested | K133: contains:DEE WHY LIBRARY | L133: DEE WHY LIBRARY DEE WHY AUS | M133: Suggested rule — confirm or edit
A134: EzyMart 460 George St Sydney | B134: 1 | C134: 2.03 | D134: 2.03 | E134: 2.03 | F134: 46262 | G134: 46262 | H134: Other | I134: Unknown | J134: unmatched | L134: EzyMart 460 George St Sydney AU | M134: No confirmed merchant rule; Budget character unknown
A135: Parramatta City Counci Parramatta | B135: 1 | C135: 2 | D135: 2 | E135: 2 | F135: 46259 | G135: 46259 | H135: Other | I135: Unknown | J135: unmatched | L135: Parramatta City Counci Parramatta NS AUS | M135: No confirmed merchant rule; Budget character unknown

Sheet Merchant Rules
A1: Enabled | B1: Priority | C1: Match Type | D1: Pattern | E1: Canonical Name | F1: Category | G1: Budget Character | H1: Status | I1: Notes
A2: yes | B2: 220 | C2: contains | D2: COSTCO GAS | E2: Costco Gas | F2: Transport | G2: Essential | H2: confirmed | I2: Fuel
A3: yes | B3: 220 | C3: contains | D3: AIRBNB | E3: Airbnb | F3: Travel | G3: Irregular | H3: confirmed | I3: Accommodation
A4: yes | B4: 220 | C4: contains | D4: IELTS | E4: IELTS | F4: Education & Professional | G4: Work/Admin | H4: confirmed | I4: Exam / professional admin
A5: yes | B5: 220 | C5: contains | D5: THE UNI OF SYDNEY | E5: University of Sydney | F5: Education & Professional | G5: Work/Admin | H5: confirmed | I5: University expense
A6: yes | B6: 220 | C6: contains | D6: WORLDWIDE INTERPRETERS | E6: Worldwide Interpreters | F6: Education & Professional | G6: Work/Admin | H6: suggested | I6: Confirm personal vs professional/admin
A7: yes | B7: 220 | C7: contains | D7: OZBARCODES | E7: OzBarcodes | F7: Education & Professional | G7: Work/Admin | H7: suggested | I7: Professional/business-like expense
A8: yes | B8: 220 | C8: contains | D8: GS1 US | E8: GS1 US | F8: Education & Professional | G8: Work/Admin | H8: suggested | I8: Professional/business-like expense
A9: yes | B9: 220 | C9: contains | D9: KWIK KOPY | E9: Kwik Kopy | F9: Education & Professional | G9: Work/Admin | H9: suggested | I9: Printing; confirm personal vs professional
A10: yes | B10: 210 | C10: contains | D10: TFNSW OPAL | E10: Transport for NSW | F10: Transport | G10: Essential | H10: confirmed | I10: Opal fare
A11: yes | B11: 210 | C11: contains | D11: TRANSPORTFORNSW | E11: Transport for NSW | F11: Transport | G11: Essential | H11: confirmed | I11: Opal / tap fare
A12: yes | B12: 210 | C12: contains | D12: LAVERTY PATHOLOGY | E12: Laverty Pathology | F12: Health & Pharmacy | G12: Essential | H12: confirmed | I12: Pathology
A13: yes | B13: 210 | C13: contains | D13: RAINBOWMEDICINE | E13: Rainbow Medicine | F13: Health & Pharmacy | G13: Essential | H13: confirmed | I13: Medical
... A58: yes | B58: 170 | C58: contains | D58: COSTCO AUBURN | E58: Costco | F58: Groceries | G58: Essential | H58: suggested | I58: Costco can be mixed; review if needed

Sheet Parser Review
A1: Date | B1: Description | C1: Amount | D1: Balance | E1: Parse Status | F1: Page | G1: Raw PDF text

Sheet Assumptions
A1: Parsing, merchant rules & budgeting assumptions
A3: Source | B3: TransactionSummary.pdf | C3: Parser | D3: PyMuPDF text + coordinate columns; no OCR / no network
A4: Statement period | B4: 2026-06-01 to 2026-09-08 | C4: Complete budget months | D4: 2026-06, 2026-07, 2026-08
A5: Opening balance | B5: 20478.71 | C5: Closing balance | D5: 25462.14
A6: Transactions | B6: 787 | C6: Parser rows needing review | D6: 0
A7: Merchant rules file | B7: merchant_rules.csv | C7: Rules loaded | D7: 57
A8: Rule precedence | B8: Money-flow rules -> highest-priority enabled merchant rule -> generic fallback -> Other | C8: Matching | D8: contains / exact / regex, case-insensitive
A9: Suggested rules | B9: Applied but kept on Merchant Review until changed to confirmed. | C9: Unmatched merchants | D9: Grouped once per merchant rather than repeated for every transaction.
A10: Budget character | B10: Separate from category: Essential / Discretionary / Irregular / Work/Admin / Unknown. | C10: Reason | D10: Prevents one-off travel/admin costs from looking like normal lifestyle burn.
A11: Reconciliation | B11: Every amount is checked against the running balance. | C11: Failure mode | D11: Workbook is not written if the statement does not reconcile.
A12: Budget | B12: Suggested category caps are still editable in BUDGET_CAPS in the script. | C12: Partial months | D12: Only complete calendar months are used when possible.

Sheet Lists
A1: Category | B1: Budget Character | C1: Rule Status
A2: Housing - Rent | B2: Essential | C2: confirmed
A3: Groceries | B3: Discretionary | C3: suggested
A4: Dining & Coffee | B4: Irregular | C4: fallback
A5: Utilities & Phone | B5: Work/Admin | C5: unmatched
A6: Transport | B6: Unknown | C6: system
A7: Fitness & Memberships | B7: Transfer
A8: Health & Pharmacy | B8: Income
A9: Shopping
A10: Beauty & Personal Care
A11: Home & Household
A12: Entertainment & Experiences
A13: Subscriptions & Donations
A14: Bank Fees
A15: Government & Admin
A16: Travel
A17: Cash Withdrawal
A18: Other
A19: Transfer Out
A20: Transfer In
... A24: Education & Professional
